Workbook

Sheet Capital Gains Tax Calculator
A1: CAPITAL GAINS TAX CALCULATOR
A2: Estimated for planning purposes only - not tax, legal, or accounting advice.
B4: Initial Value | E4: Sale Value | H4: Length of Ownership
C5: 10000 | F5: 50000 | I5: More than a year
B7: Location (State) | E7: Annual Income | H7: Filing Status
C8: New Jersey | F8: 200000 | I8: Married Filing Jointly
B9: Tax Year
C10: 2025
B12: ADVANCED (optional - click the [+] in the row-number margin to expand)
B13: 401(k) Contribution | E13: IRA Contribution | H13: Itemized Deductions
C14: 0 | F14: 0 | I14: 0
B15: Number of Personal Exemptions (state only) | E15: Locality / City (optional)
C16: 0 | F16: None / Not Applicable
B18: =C63
A21: YOUR CAPITAL GAINS TAXES
B22: Tax Type | D22: Marginal Tax Rate | F22: Effective Tax Rate | H22: Tax Amount
B23: Federal | D23: =C64 | F23: =C65 | H23: =C56
B24: State | D24: =C66 | F24: =C67 | H24: =C61
B25: Local | D25: =C42 | F25: =C68 | H25: =C62
B26: Total Estimated Tax | H26: =C63
B28: Estimated for financial-planning purposes only. This calculator is not tax, legal, or accounting advice. Actual tax liability may differ based on individual circumstances, deductions, credits, tax elections, state/local rules, and other factors. Consult a qualified tax professional before making tax-related decisions. "Federal" includes the Net Investment Income Tax (3.8%) where applicable.
B32: Full calculation detail is available below for your advisor. Click the [+] in the row-number margin to expand.
A34: CALCULATION DETAIL (grouped - click + to expand)
B36: Standard Deduction (add-back for MAGI estimate) | C36: =INDEX('Tax Rates & Assumptions'!$D$28:$D$35,L42) | K36: Filing Status | L36: =I8
B37: Capital Loss Limit vs. Ordinary Income | C37: =INDEX('Tax Rates & Assumptions'!$D$39:$D$42,L41) | K37: Tax Year | L37: =C10
B38: NIIT Threshold | C38: =INDEX('Tax Rates & Assumptions'!$B$39:$B$42,L41) | K38: Federal Key | L38: =L37&"|"&L36
B39: NIIT Rate | C39: =INDEX('Tax Rates & Assumptions'!$C$39:$C$42,L41) | K39: Fed Bracket Row# | L39: =MATCH(L38,'Tax Rates & Assumptions'!$C$6:$C$13,0)
B40: State Standard Deduction | C40: =IF(L45="MFJ",INDEX('Tax Rates & Assumptions'!$E$46:$E$77,L48),INDEX('Tax Rates & Assumptions'!$D$46:$D$77,L48)) | K40: LTCG Bracket Row# | L40: =MATCH(L38,'Tax Rates & Assumptions'!$C$17:$C$24,0)
B41: Personal Exemption Amount (per exemption, state) | C41: =INDEX('Tax Rates & Assumptions'!$C$164:$C$164,1) | K41: Status Row# (NIIT/CapLoss) | L41: =MATCH(L36,'Tax Rates & Assumptions'!$A$39:$A$42,0)
B42: Local Tax Rate | C42: =IF(L50=0,0,INDEX('Tax Rates & Assumptions'!$D$148:$D$161,L50)) | K42: StdDed Row# | L42: =MATCH(L38,'Tax Rates & Assumptions'!$C$28:$C$35,0)
B43: Capital Gain / (Loss) on Sale | C43: =(F5-C5) | K43: State Name | L43: =C8
B44: Is Long-Term? | C44: =IF(I5="More than a year",1,0) | K44: State Code | L44: =INDEX('Tax Rates & Assumptions'!$A$46:$A$77,MATCH(L43,'Tax Rates & Assumptions'!$B$46:$B$77,0))
B45: Ordinary-Taxed Portion (short-term gain, or loss deduction capped) | C45: =IF(C43>=0,IF(C44=1,0,C43),MAX(C43,-C37)) | K45: State Category | L45: =IF(L36="Married Filing Jointly","MFJ","Single")
B46: Preferential-Rate Portion (long-term gain) | C46: =IF(C43>=0,IF(C44=1,C43,0),0) | K46: State Key | L46: =L44&"|"&L45
B47: Taxable Income Before the Gain | C47: =MAX(0,F8-C14-F14-MAX(I14,INDEX('Tax Rates & Assumptions'!$D$28:$D$35,L42))) | K47: State Bracket Row# | L47: =MATCH(L46,'Tax Rates & Assumptions'!$C$81:$C$144,0)
B48: Taxable Income Including the Gain | C48: =MAX(0,C47+C45) | K48: State Master Row# | L48: =MATCH(L44,'Tax Rates & Assumptions'!$A$46:$A$77,0)
B49: Federal Tax on Income Alone (no gain) | C49: =SUMPRODUCT((C47>$M$53:$M$59)*($L$53:$L$59)*(MIN(C47,$N$53:$N$59)-$M$53:$M$59)) | K49: Locality Name | L49: =F16
B50: Federal Tax on Income Including the Gain | C50: =SUMPRODUCT((C48>$M$53:$M$59)*($L$53:$L$59)*(MIN(C48,$N$53:$N$59)-$M$53:$M$59)) | K50: Locality Row# | L50: =IFERROR(MATCH(L49,'Tax Rates & Assumptions'!$B$148:$B$161,0),0)
B51: Federal Tax on Ordinary Portion of the Gain | C51: =C50-C49
B52: Federal Tax on Preferential (Long-Term) Portion (stacked) | C52: =SUMPRODUCT($L$62:$L$64*(MAX(0,MIN((C48+C46),$N$62:$N$64)-MAX(C48,$M$62:$M$64)))) | K52: Federal Ordinary Brackets
B53: MAGI Estimate (Taxable Income + Std. Ded. Add-Back + Net Gain) | C53: =(C47+C36+C45+C46) | L53: =INDEX('Tax Rates & Assumptions'!D$6:D$1005,L39) | M53: =INDEX('Tax Rates & Assumptions'!E$6:E$1005,L39) | N53: =INDEX('Tax Rates & Assumptions'!F$6:F$1005,L39)
B54: Net Investment Income (the modeled gain) | C54: =MAX(0,C45+C46) | L54: =INDEX('Tax Rates & Assumptions'!G$6:G$1005,L39) | M54: =INDEX('Tax Rates & Assumptions'!H$6:H$1005,L39) | N54: =INDEX('Tax Rates & Assumptions'!I$6:I$1005,L39)
B55: NIIT | C55: =C39*MIN(C54,MAX(0,C53-C38)) | L55: =INDEX('Tax Rates & Assumptions'!J$6:J$1005,L39) | M55: =INDEX('Tax Rates & Assumptions'!K$6:K$1005,L39) | N55: =INDEX('Tax Rates & Assumptions'!L$6:L$1005,L39)
B56: Total Federal Tax From the Gain (incl. NIIT) | C56: =(C51+C52+C55) | L56: =INDEX('Tax Rates & Assumptions'!M$6:M$1005,L39) | M56: =INDEX('Tax Rates & Assumptions'!N$6:N$1005,L39) | N56: =INDEX('Tax Rates & Assumptions'!O$6:O$1005,L39)
B57: State Taxable Income Before the Gain | C57: =MAX(0,C47-C40-C16*C41) | L57: =INDEX('Tax Rates & Assumptions'!P$6:P$1005,L39) | M57: =INDEX('Tax Rates & Assumptions'!Q$6:Q$1005,L39) | N57: =INDEX('Tax Rates & Assumptions'!R$6:R$1005,L39)
B58: State Taxable Income Including the Gain | C58: =MAX(0,C47+C45+C46-C40-C16*C41) | L58: =INDEX('Tax Rates & Assumptions'!S$6:S$1005,L39) | M58: =INDEX('Tax Rates & Assumptions'!T$6:T$1005,L39) | N58: =INDEX('Tax Rates & Assumptions'!U$6:U$1005,L39)
B59: State Tax on Income Alone | C59: =IF(L44="OTHER",0,SUMPRODUCT((C57>$M$67:$M$74)*($L$67:$L$74)*(MIN(C57,$N$67:$N$74)-$M$67:$M$74))) | L59: =INDEX('Tax Rates & Assumptions'!V$6:V$1005,L39) | M59: =INDEX('Tax Rates & Assumptions'!W$6:W$1005,L39) | N59: =INDEX('Tax Rates & Assumptions'!X$6:X$1005,L39)
B60: State Tax on Income Including the Gain | C60: =IF(L44="OTHER",0,SUMPRODUCT((C58>$M$67:$M$74)*($L$67:$L$74)*(MIN(C58,$N$67:$N$74)-$M$67:$M$74)))
B61: State Tax From the Gain | C61: =(C60-C59) | K61: LTCG Brackets
B62: Local Tax From the Gain | C62: =C42*MAX(0,C43) | L62: =INDEX('Tax Rates & Assumptions'!D$17:D$1016,L40) | M62: =INDEX('Tax Rates & Assumptions'!E$17:E$1016,L40) | N62: =INDEX('Tax Rates & Assumptions'!F$17:F$1016,L40)
B63: Total Estimated Tax | C63: =(C56+C61+C62) | L63: =INDEX('Tax Rates & Assumptions'!G$17:G$1016,L40) | M63: =INDEX('Tax Rates & Assumptions'!H$17:H$1016,L40) | N63: =INDEX('Tax Rates & Assumptions'!I$17:I$1016,L40)
B64: Federal Marginal Rate Applied to the Gain | C64: =IF(AND(C43>=0,C44=1),IFERROR(INDEX($L$62:$L$64,MATCH(C48,$M$62:$M$64,1)),0),IFERROR(INDEX($L$53:$L$59,MATCH(C48,$M$53:$M$59,1)),0)) | L64: =INDEX('Tax Rates & Assumptions'!J$17:J$1016,L40) | M64: =INDEX('Tax Rates & Assumptions'!K$17:K$1016,L40) | N64: =INDEX('Tax Rates & Assumptions'!L$17:L$1016,L40)
B65: Federal Effective Rate on the Gain | C65: =IFERROR(C56/C43,0)
B66: State Marginal Rate Applied to the Gain | C66: =IF(L44="OTHER",0,IFERROR(INDEX($L$67:$L$74,MATCH(C58,$M$67:$M$74,1)),0)) | K66: State Brackets
B67: State Effective Rate on the Gain | C67: =IFERROR(C61/C43,0) | L67: =INDEX('Tax Rates & Assumptions'!D$81:D$1080,L47) | M67: =INDEX('Tax Rates & Assumptions'!E$81:E$1080,L47) | N67: =INDEX('Tax Rates & Assumptions'!F$81:F$1080,L47)
B68: Local Effective Rate on the Gain | C68: =IFERROR(C62/C43,0) | L68: =INDEX('Tax Rates & Assumptions'!G$81:G$1080,L47) | M68: =INDEX('Tax Rates & Assumptions'!H$81:H$1080,L47) | N68: =INDEX('Tax Rates & Assumptions'!I$81:I$1080,L47)
L69: =INDEX('Tax Rates & Assumptions'!J$81:J$1080,L47) | M69: =INDEX('Tax Rates & Assumptions'!K$81:K$1080,L47) | N69: =INDEX('Tax Rates & Assumptions'!L$81:L$1080,L47)
L70: =INDEX('Tax Rates & Assumptions'!M$81:M$1080,L47) | M70: =INDEX('Tax Rates & Assumptions'!N$81:N$1080,L47) | N70: =INDEX('Tax Rates & Assumptions'!O$81:O$1080,L47)
L71: =INDEX('Tax Rates & Assumptions'!P$81:P$1080,L47) | M71: =INDEX('Tax Rates & Assumptions'!Q$81:Q$1080,L47) | N71: =INDEX('Tax Rates & Assumptions'!R$81:R$1080,L47)
L72: =INDEX('Tax Rates & Assumptions'!S$81:S$1080,L47) | M72: =INDEX('Tax Rates & Assumptions'!T$81:T$1080,L47) | N72: =INDEX('Tax Rates & Assumptions'!U$81:U$1080,L47)
L73: =INDEX('Tax Rates & Assumptions'!V$81:V$1080,L47) | M73: =INDEX('Tax Rates & Assumptions'!W$81:W$1080,L47) | N73: =INDEX('Tax Rates & Assumptions'!X$81:X$1080,L47)
L74: =INDEX('Tax Rates & Assumptions'!Y$81:Y$1080,L47) | M74: =INDEX('Tax Rates & Assumptions'!Z$81:Z$1080,L47) | N74: =INDEX('Tax Rates & Assumptions'!AA$81:AA$1080,L47)

Sheet Tax Rates & Assumptions
A1: TAX RATES & ASSUMPTIONS
A2: This tab stores every tax-law figure used by the Capital Gains Tax Estimator (federal brackets, deduction amounts, thresholds, and state rates), organized by tax year. Update it to refresh figures for a new tax year or a state not yet listed - no formulas on the calculator tab need to change.
A4: Federal Ordinary Income Tax Brackets
A5: Year | B5: Filing Status | C5: Key | D5: Rate 1 | E5: Min 1 | F5: Max 1 | G5: Rate 2 | H5: Min 2 | I5: Max 2 | J5: Rate 3 | K5: Min 3 | L5: Max 3 | M5: Rate 4 | N5: Min 4 | O5: Max 4 | P5: Rate 5 | Q5: Min 5 | R5: Max 5 | S5: Rate 6 | T5: Min 6 | U5: Max 6 | V5: Rate 7 | W5: Min 7 | X5: Max 7
A6: 2024 | B6: Single | C6: =A6&"|"&B6 | D6: 0.1 | E6: 0 | F6: =H6 | G6: 0.12 | H6: 11600 | I6: =K6 | J6: 0.22 | K6: 47150 | L6: =N6 | M6: 0.24 | N6: 100525 | O6: =Q6 | P6: 0.32 | Q6: 191950 | R6: =T6 | S6: 0.35 | T6: 243725 | U6: =W6 | V6: 0.37 | W6: 609350 | X6: 999999999
A7: 2024 | B7: Married Filing Jointly | C7: =A7&"|"&B7 | D7: 0.1 | E7: 0 | F7: =H7 | G7: 0.12 | H7: 23200 | I7: =K7 | J7: 0.22 | K7: 94300 | L7: =N7 | M7: 0.24 | N7: 201050 | O7: =Q7 | P7: 0.32 | Q7: 383900 | R7: =T7 | S7: 0.35 | T7: 487450 | U7: =W7 | V7: 0.37 | W7: 731200 | X7: 999999999
A8: 2024 | B8: Married Filing Separately | C8: =A8&"|"&B8 | D8: 0.1 | E8: 0 | F8: =H8 | G8: 0.12 | H8: 11600 | I8: =K8 | J8: 0.22 | K8: 47150 | L8: =N8 | M8: 0.24 | N8: 100525 | O8: =Q8 | P8: 0.32 | Q8: 191950 | R8: =T8 | S8: 0.35 | T8: 243725 | U8: =W8 | V8: 0.37 | W8: 365600 | X8: 999999999
A9: 2024 | B9: Head of Household | C9: =A9&"|"&B9 | D9: 0.1 | E9: 0 | F9: =H9 | G9: 0.12 | H9: 16550 | I9: =K9 | J9: 0.22 | K9: 63100 | L9: =N9 | M9: 0.24 | N9: 100500 | O9: =Q9 | P9: 0.32 | Q9: 191950 | R9: =T9 | S9: 0.35 | T9: 243700 | U9: =W9 | V9: 0.37 | W9: 609350 | X9: 999999999
A10: 2025 | B10: Single | C10: =A10&"|"&B10 | D10: 0.1 | E10: 0 | F10: =H10 | G10: 0.12 | H10: 11925 | I10: =K10 | J10: 0.22 | K10: 48475 | L10: =N10 | M10: 0.24 | N10: 103350 | O10: =Q10 | P10: 0.32 | Q10: 197300 | R10: =T10 | S10: 0.35 | T10: 250525 | U10: =W10 | V10: 0.37 | W10: 626350 | X10: 999999999
A11: 2025 | B11: Married Filing Jointly | C11: =A11&"|"&B11 | D11: 0.1 | E11: 0 | F11: =H11 | G11: 0.12 | H11: 23850 | I11: =K11 | J11: 0.22 | K11: 96950 | L11: =N11 | M11: 0.24 | N11: 206700 | O11: =Q11 | P11: 0.32 | Q11: 394600 | R11: =T11 | S11: 0.35 | T11: 501050 | U11: =W11 | V11: 0.37 | W11: 751600 | X11: 999999999
A12: 2025 | B12: Married Filing Separately | C12: =A12&"|"&B12 | D12: 0.1 | E12: 0 | F12: =H12 | G12: 0.12 | H12: 11925 | I12: =K12 | J12: 0.22 | K12: 48475 | L12: =N12 | M12: 0.24 | N12: 103350 | O12: =Q12 | P12: 0.32 | Q12: 197300 | R12: =T12 | S12: 0.35 | T12: 250525 | U12: =W12 | V12: 0.37 | W12: 375800 | X12: 999999999
A13: 2025 | B13: Head of Household | C13: =A13&"|"&B13 | D13: 0.1 | E13: 0 | F13: =H13 | G13: 0.12 | H13: 17000 | I13: =K13 | J13: 0.22 | K13: 64850 | L13: =N13 | M13: 0.24 | N13: 103350 | O13: =Q13 | P13: 0.32 | Q13: 197300 | R13: =T13 | S13: 0.35 | T13: 250500 | U13: =W13 | V13: 0.37 | W13: 626350 | X13: 999999999
A15: Long-Term Capital Gains Brackets (0% / 15% / 20%)
A16: Year | B16: Filing Status | C16: Key | D16: Rate 1 | E16: Min 1 | F16: Max 1 | G16: Rate 2 | H16: Min 2 | I16: Max 2 | J16: Rate 3 | K16: Min 3 | L16: Max 3
A17: 2024 | B17: Single | C17: =A17&"|"&B17 | D17: 0 | E17: 0 | F17: =H17 | G17: 0.15 | H17: 47025 | I17: =K17 | J17: 0.2 | K17: 518900 | L17: 999999999
A18: 2024 | B18: Married Filing Jointly | C18: =A18&"|"&B18 | D18: 0 | E18: 0 | F18: =H18 | G18: 0.15 | H18: 94050 | I18: =K18 | J18: 0.2 | K18: 583750 | L18: 999999999
A19: 2024 | B19: Married Filing Separately | C19: =A19&"|"&B19 | D19: 0 | E19: 0 | F19: =H19 | G19: 0.15 | H19: 47025 | I19: =K19 | J19: 0.2 | K19: 291850 | L19: 999999999
A20: 2024 | B20: Head of Household | C20: =A20&"|"&B20 | D20: 0 | E20: 0 | F20: =H20 | G20: 0.15 | H20: 63000 | I20: =K20 | J20: 0.2 | K20: 551350 | L20: 999999999
A21: 2025 | B21: Single | C21: =A21&"|"&B21 | D21: 0 | E21: 0 | F21: =H21 | G21: 0.15 | H21: 48350 | I21: =K21 | J21: 0.2 | K21: 533400 | L21: 999999999
A22: 2025 | B22: Married Filing Jointly | C22: =A22&"|"&B22 | D22: 0 | E22: 0 | F22: =H22 | G22: 0.15 | H22: 96700 | I22: =K22 | J22: 0.2 | K22: 600050 | L22: 999999999
A23: 2025 | B23: Married Filing Separately | C23: =A23&"|"&B23 | D23: 0 | E23: 0 | F23: =H23 | G23: 0.15 | H23: 48350 | I23: =K23 | J23: 0.2 | K23: 300000 | L23: 999999999
A24: 2025 | B24: Head of Household | C24: =A24&"|"&B24 | D24: 0 | E24: 0 | F24: =H24 | G24: 0.15 | H24: 64750 | I24: =K24 | J24: 0.2 | K24: 566700 | L24: 999999999
A26: Standard Deduction
A27: Year | B27: Filing Status | C27: Key | D27: Standard Deduction
A28: 2024 | B28: Single | C28: =A28&"|"&B28 | D28: 14600
A29: 2024 | B29: Married Filing Jointly | C29: =A29&"|"&B29 | D29: 29200
A30: 2024 | B30: Married Filing Separately | C30: =A30&"|"&B30 | D30: 14600
A31: 2024 | B31: Head of Household | C31: =A31&"|"&B31 | D31: 21900
A32: 2025 | B32: Single | C32: =A32&"|"&B32 | D32: 15000
A33: 2025 | B33: Married Filing Jointly | C33: =A33&"|"&B33 | D33: 30000
A34: 2025 | B34: Married Filing Separately | C34: =A34&"|"&B34 | D34: 15000
A35: 2025 | B35: Head of Household | C35: =A35&"|"&B35 | D35: 22500
A37: NIIT Thresholds & Capital-Loss Deduction Limit (fixed by statute)
A38: Filing Status | B38: NIIT MAGI Threshold | C38: NIIT Rate | D38: Annual Capital-Loss Deduction Limit
A39: Single | B39: 200000 | C39: 0.038 | D39: 3000
A40: Married Filing Jointly | B40: 250000 | C40: 0.038 | D40: 3000
A41: Married Filing Separately | B41: 125000 | C41: 0.038 | D41: 1500
A42: Head of Household | B42: 200000 | C42: 0.038 | D42: 3000
A44: State Master List & Capital-Gains Treatment
A45: State Code | B45: State Name | C45: Tax Type | D45: Std. Deduction (Single) | E45: Std. Deduction (MFJ) | F45: Capital-Gains Treatment | G45: Notes / Simplifications
A46: FL | B46: Florida | C46: None | D46: 0 | E46: 0 | F46: No state income tax | G46: No state income tax.
A47: TX | B47: Texas | C47: None | D47: 0 | E47: 0 | F47: No state income tax | G47: No state income tax.
A48: WA | B48: Washington | C48: None | D48: 0 | E48: 0 | F48: No state income tax | G48: No state income tax (capital gains excise tax on high earners not modeled).
A49: NV | B49: Nevada | C49: None | D49: 0 | E49: 0 | F49: No state income tax | G49: No state income tax.
A50: WY | B50: Wyoming | C50: None | D50: 0 | E50: 0 | F50: No state income tax | G50: No state income tax.
A51: SD | B51: South Dakota | C51: None | D51: 0 | E51: 0 | F51: No state income tax | G51: No state income tax.
A52: AK | B52: Alaska | C52: None | D52: 0 | E52: 0 | F52: No state income tax | G52: No state income tax.
A53: TN | B53: Tennessee | C53: None | D53: 0 | E53: 0 | F53: No state income tax | G53: No state income tax.
A54: CO | B54: Colorado | C54: Flat | D54: 0 | E54: 0 | F54: Taxed as ordinary income (no preferential state rate) | G54: Flat rate; SS generally subtracted.
A55: IL | B55: Illinois | C55: Flat | D55: 0 | E55: 0 | F55: Taxed as ordinary income (no preferential state rate) | G55: Flat rate; retirement income generally exempt; SS exempt.
A56: IN | B56: Indiana | C56: Flat | D56: 0 | E56: 0 | F56: Taxed as ordinary income (no preferential state rate) | G56: Flat rate.
A57: MI | B57: Michigan | C57: Flat | D57: 0 | E57: 0 | F57: Taxed as ordinary income (no preferential state rate) | G57: Flat rate; retirement income partially/fully exempt depending on birth year (simplified: exempt).
... A77: OTHER | B77: Other (Manual Entry) | C77: Manual | D77: 0 | E77: 0 | F77: Taxed as ordinary income | G77: Uses the manual effective state tax rate entered on the calculator tab.
A79: State Income Tax Brackets (unified format; category Single covers Single/MFS/HOH, MFJ covers MFJ)
A80: State Code | B80: Filing Category | C80: Key | D80: Rate 1 | E80: Min 1 | F80: Max 1 | G80: Rate 2 | H80: Min 2 | I80: Max 2 | J80: Rate 3 | K80: Min 3 | L80: Max 3 | M80: Rate 4 | N80: Min 4 | O80: Max 4 | P80: Rate 5 | Q80: Min 5 | R80: Max 5 | S80: Rate 6 | T80: Min 6 | U80: Max 6 | V80: Rate 7 | W80: Min 7 | X80: Max 7 | Y80: Rate 8 | Z80: Min 8 | AA80: Max 8
A81: FL | B81: Single | C81: =A81&"|"&B81 | D81: 0 | E81: 0 | F81: =H81 | G81: 0 | H81: 999999999 | I81: =K81 | J81: 0 | K81: 999999999 | L81: =N81 | M81: 0 | N81: 999999999 | O81: =Q81 | P81: 0 | Q81: 999999999 | R81: =T81 | S81: 0 | T81: 999999999 | U81: =W81 | V81: 0 | W81: 999999999 | X81: =Z81 | Y81: 0 | Z81: 999999999 | AA81: 999999999
A82: FL | B82: MFJ | C82: =A82&"|"&B82 | D82: 0 | E82: 0 | F82: =H82 | G82: 0 | H82: 999999999 | I82: =K82 | J82: 0 | K82: 999999999 | L82: =N82 | M82: 0 | N82: 999999999 | O82: =Q82 | P82: 0 | Q82: 999999999 | R82: =T82 | S82: 0 | T82: 999999999 | U82: =W82 | V82: 0 | W82: 999999999 | X82: =Z82 | Y82: 0 | Z82: 999999999 | AA82: 999999999
A83: TX | B83: Single | C83: =A83&"|"&B83 | D83: 0 | E83: 0 | F83: =H83 | G83: 0 | H83: 999999999 | I83: =K83 | J83: 0 | K83: 999999999 | L83: =N83 | M83: 0 | N83: 999999999 | O83: =Q83 | P83: 0 | Q83: 999999999 | R83: =T83 | S83: 0 | T83: 999999999 | U83: =W83 | V83: 0 | W83: 999999999 | X83: =Z83 | Y83: 0 | Z83: 999999999 | AA83: 999999999
A84: TX | B84: MFJ | C84: =A84&"|"&B84 | D84: 0 | E84: 0 | F84: =H84 | G84: 0 | H84: 999999999 | I84: =K84 | J84: 0 | K84: 999999999 | L84: =N84 | M84: 0 | N84: 999999999 | O84: =Q84 | P84: 0 | Q84: 999999999 | R84: =T84 | S84: 0 | T84: 999999999 | U84: =W84 | V84: 0 | W84: 999999999 | X84: =Z84 | Y84: 0 | Z84: 999999999 | AA84: 999999999
A85: WA | B85: Single | C85: =A85&"|"&B85 | D85: 0 | E85: 0 | F85: =H85 | G85: 0 | H85: 999999999 | I85: =K85 | J85: 0 | K85: 999999999 | L85: =N85 | M85: 0 | N85: 999999999 | O85: =Q85 | P85: 0 | Q85: 999999999 | R85: =T85 | S85: 0 | T85: 999999999 | U85: =W85 | V85: 0 | W85: 999999999 | X85: =Z85 | Y85: 0 | Z85: 999999999 | AA85: 999999999
A86: WA | B86: MFJ | C86: =A86&"|"&B86 | D86: 0 | E86: 0 | F86: =H86 | G86: 0 | H86: 999999999 | I86: =K86 | J86: 0 | K86: 999999999 | L86: =N86 | M86: 0 | N86: 999999999 | O86: =Q86 | P86: 0 | Q86: 999999999 | R86: =T86 | S86: 0 | T86: 999999999 | U86: =W86 | V86: 0 | W86: 999999999 | X86: =Z86 | Y86: 0 | Z86: 999999999 | AA86: 999999999
A87: NV | B87: Single | C87: =A87&"|"&B87 | D87: 0 | E87: 0 | F87: =H87 | G87: 0 | H87: 999999999 | I87: =K87 | J87: 0 | K87: 999999999 | L87: =N87 | M87: 0 | N87: 999999999 | O87: =Q87 | P87: 0 | Q87: 999999999 | R87: =T87 | S87: 0 | T87: 999999999 | U87: =W87 | V87: 0 | W87: 999999999 | X87: =Z87 | Y87: 0 | Z87: 999999999 | AA87: 999999999
A88: NV | B88: MFJ | C88: =A88&"|"&B88 | D88: 0 | E88: 0 | F88: =H88 | G88: 0 | H88: 999999999 | I88: =K88 | J88: 0 | K88: 999999999 | L88: =N88 | M88: 0 | N88: 999999999 | O88: =Q88 | P88: 0 | Q88: 999999999 | R88: =T88 | S88: 0 | T88: 999999999 | U88: =W88 | V88: 0 | W88: 999999999 | X88: =Z88 | Y88: 0 | Z88: 999999999 | AA88: 999999999
A89: WY | B89: Single | C89: =A89&"|"&B89 | D89: 0 | E89: 0 | F89: =H89 | G89: 0 | H89: 999999999 | I89: =K89 | J89: 0 | K89: 999999999 | L89: =N89 | M89: 0 | N89: 999999999 | O89: =Q89 | P89: 0 | Q89: 999999999 | R89: =T89 | S89: 0 | T89: 999999999 | U89: =W89 | V89: 0 | W89: 999999999 | X89: =Z89 | Y89: 0 | Z89: 999999999 | AA89: 999999999
A90: WY | B90: MFJ | C90: =A90&"|"&B90 | D90: 0 | E90: 0 | F90: =H90 | G90: 0 | H90: 999999999 | I90: =K90 | J90: 0 | K90: 999999999 | L90: =N90 | M90: 0 | N90: 999999999 | O90: =Q90 | P90: 0 | Q90: 999999999 | R90: =T90 | S90: 0 | T90: 999999999 | U90: =W90 | V90: 0 | W90: 999999999 | X90: =Z90 | Y90: 0 | Z90: 999999999 | AA90: 999999999
A91: SD | B91: Single | C91: =A91&"|"&B91 | D91: 0 | E91: 0 | F91: =H91 | G91: 0 | H91: 999999999 | I91: =K91 | J91: 0 | K91: 999999999 | L91: =N91 | M91: 0 | N91: 999999999 | O91: =Q91 | P91: 0 | Q91: 999999999 | R91: =T91 | S91: 0 | T91: 999999999 | U91: =W91 | V91: 0 | W91: 999999999 | X91: =Z91 | Y91: 0 | Z91: 999999999 | AA91: 999999999
A92: SD | B92: MFJ | C92: =A92&"|"&B92 | D92: 0 | E92: 0 | F92: =H92 | G92: 0 | H92: 999999999 | I92: =K92 | J92: 0 | K92: 999999999 | L92: =N92 | M92: 0 | N92: 999999999 | O92: =Q92 | P92: 0 | Q92: 999999999 | R92: =T92 | S92: 0 | T92: 999999999 | U92: =W92 | V92: 0 | W92: 999999999 | X92: =Z92 | Y92: 0 | Z92: 999999999 | AA92: 999999999
... A144: OTHER | B144: MFJ | C144: =A144&"|"&B144 | D144: 0 | E144: 0 | F144: =H144 | G144: 0 | H144: 999999999 | I144: =K144 | J144: 0 | K144: 999999999 | L144: =N144 | M144: 0 | N144: 999999999 | O144: =Q144 | P144: 0 | Q144: 999999999 | R144: =T144 | S144: 0 | T144: 999999999 | U144: =W144 | V144: 0 | W144: 999999999 | X144: =Z144 | Y144: 0 | Z144: 999999999 | AA144: 999999999
A146: Local / Municipal Tax Table
A147: Locality Code | B147: Locality Name | C147: State | D147: Rate | E147: Notes
A148: NYC | B148: New York City | C148: NY | D148: 0.03648 | E148: Approximate blended NYC resident rate.
A149: YONK | B149: Yonkers (NY) | C149: NY | D149: 0.1675 | E149: Resident surcharge as % of NY State tax.
A150: PHIL | B150: Philadelphia, PA | C150: PA | D150: 0.0375 | E150: Philadelphia wage tax (resident).
A151: PIT | B151: Pittsburgh, PA | C151: PA | D151: 0.03 | E151: Local earned income tax (approx.).
A152: DET | B152: Detroit, MI | C152: MI | D152: 0.024 | E152: Detroit resident income tax.
A153: COL | B153: Columbus, OH | C153: OH | D153: 0.025 | E153: Ohio municipal income tax (approx.).
A154: CIN | B154: Cincinnati, OH | C154: OH | D154: 0.019 | E154: Ohio municipal income tax (approx.).
A155: CLE | B155: Cleveland, OH | C155: OH | D155: 0.025 | E155: Ohio municipal income tax (approx.).
A156: MDCO | B156: Maryland County (avg.) | C156: MD | D156: 0.32 | E156: Average MD county piggyback tax as % of state taxable income equivalent (approx.).
A157: INCO | B157: Indiana County (avg.) | C157: IN | D157: 0.0165 | E157: Average Indiana county income tax (approx.).
A158: KCMO | B158: Kansas City, MO | C158: MO | D158: 0.01 | E158: Local earnings tax.
A159: STL | B159: St. Louis, MO | C159: MO | D159: 0.01 | E159: Local earnings tax.
A160: NONE | B160: None / Not Applicable | D160: 0 | E160: No local tax.
A161: OTHER | B161: Other (Manual Entry) | D161: 0 | E161: Enter a custom local rate on the Inputs tab.
A163: Personal Exemption Assumption
A164: Generic State Personal Exemption Amount (per exemption) | C164: 1000
A165: Federal personal exemptions are suspended (set to $0) under current law. Most states that still allow a personal exemption use their own amount; this workbook applies one generic per-exemption reduction to state taxable income for simplicity - update the figure above or refine per state as needed.
A168: DISCLAIMER: Estimated for financial-planning purposes only. This calculator is not tax, legal, or accounting advice. Actual tax liability may differ based on individual circumstances, deductions, credits, tax elections, state/local rules, and other factors. Consult a qualified tax professional before making tax-related decisions.
A174: Key Assumptions
A175: • Tax Year Coverage: 2024 and 2025. Every bracket, deduction, and threshold used by the calculator lives on this tab; nothing is hardcoded in the formulas on the Capital Gains Tax Estimator tab.
A176: • Short-term and long-term gains/losses are netted using standard IRC Sec. 1211/1222 ordering (Form 8949 / Schedule D concepts): a net short-term loss first offsets net long-term gain (and vice versa) before any loss is allowed against ordinary income, capped at the annual limit above (with the remainder carried forward indefinitely). Long-term capital gains are 'stacked' on top of ordinary taxable income when applying the 0%/15%/20% preferential brackets, so they are taxed at the rate(s) that actually apply given the household's total income - not an average rate. Short-term gains are taxed as ordinary income.
A177: • The Net Investment Income Tax (3.8%) MAGI thresholds are fixed by statute and have not been inflation-adjusted since enactment (2013). MAGI is approximated as taxable ordinary income plus the net capital gain being modeled.
A178: • 31 states plus Washington D.C. are modeled individually (no-tax, flat-tax, and progressive structures), plus a manual-entry option for any other state - not all 50 states are included. State brackets use two filing categories: 'Single' (applied to Single, Married Filing Separately, and Head of Household) and 'MFJ' (applied to Married Filing Jointly).
A179: • All states are assumed to tax capital gains as ordinary income (i.e., no separate state preferential capital-gains rate), which is accurate for the large majority of states. State tax uses a state-specific standard deduction where available; it does not model every state's exemption or credit nuance - this is a planning estimate, not a full state tax return.
A180: • Tax-loss harvesting losses entered in the What-If section are assumed to be long-term in character (the common case for most portfolios).
A181: • This workbook does not model AMT, Qualified Business Income deductions, or every state/local nuance.
