Workbook

Sheet Div & Interest Tax Calculator
A1: DIVIDEND & INTEREST INCOME TAX CALCULATOR
A2: Estimated federal and state tax on dividends (qualified and non-qualified) and interest income (taxable, U.S. Treasury, and tax-exempt municipal) -- for financial-planning discussion purposes only. This is not tax, legal, or accounting advice. For realized gains/losses, see the companion Capital Gains Tax Estimator.
A4: CLIENT INPUTS (enter only the fields that apply)
B5: Tax Year | E5: Filing Status | H5: State of Residence
C6: 2025 | F6: Married Filing Jointly | I6: New Jersey
B7: Total Household Income (wages/salary; excludes the portfolio income below) | E7: Pre-Tax Deductions (401(k), HSA, etc.) | H7: Non-Qualified (Ordinary) Dividends
C8: 200000 | F8: 10000 | I8: 5000
B9: Qualified Dividends | E9: Taxable Interest (bank, CDs, corporate bonds, etc.) | H9: U.S. Treasury / Government Interest
C10: 15000 | F10: 8000 | I10: 4000
B11: Tax-Exempt Municipal Bond Interest -- issued by your state of residence | E11: Tax-Exempt Municipal Bond Interest -- issued by other states
C12: 0 | F12: 0
A14: PORTFOLIO INCOME
B15: Total Household Income | G15: =C8 -> 200000
B16: Pre-Tax Deductions | G16: =F8 -> 10000
B17: Standard Deduction (auto, based on tax year & filing status) | G17: =L65 -> 30000
B18: Estimated Taxable Income Before Portfolio Income | G18: =L99 -> 160000
B19: Non-Qualified (Ordinary) Dividends | G19: =I8 -> 5000
B20: Qualified Dividends | G20: =C10 -> 15000
B21: Taxable Interest (incl. U.S. Treasury) | G21: =(F10+I10) -> 12000
B22: Tax-Exempt Municipal Bond Interest (informational; not federally taxed) | G22: =(C12+F12) -> 0
B23: Total Taxable Portfolio Income -- Overall | G23: =L121 -> 32000
A25: ESTIMATED FEDERAL TAX
B26: Tax on Non-Qualified Dividends & Interest (ordinary rates) | G26: =L104 -> 3740
B27: Tax on Qualified Dividends (0% / 15% / 20%, stacked) | G27: =L107 -> 2250
B28: Net Investment Income Tax (NIIT, 3.8%, when applicable) | G28: =L110 -> 0
B29: Total Estimated Federal Tax | G29: =L111 -> 5990
A31: ESTIMATED STATE TAX
B32: State | G32: =I6 -> New Jersey
B33: State Tax Treatment | G33: =L74 -> Progressive brackets (taxed as ordinary income)
B34: Estimated State Tax on Portfolio Income | G34: =L119 -> 1783.6
A36: TOTAL
B37: Total Estimated Tax on Portfolio Income (Federal + State) | G37: =L120 -> 7773.6
B38: Effective Tax Rate on Portfolio Income | G38: =L122 -> 0.242925
B39: Estimated After-Tax Portfolio Income | G39: =L123 -> 24226.4
A41: DISCLAIMER: This calculator produces a planning-level ESTIMATE only. It is not tax, legal, or accounting advice and should not be relied upon to prepare an actual tax return. It does not account for every individual tax situation -- among other things, it does not model AMT (including the municipal-bond private-activity-bond preference item), tax credits, itemized deductions, self-employment or additional Medicare tax, the taxation of Social Security benefits, ACA premium tax credit MAGI effects, or local/municipal income taxes (other than where noted). U.S. Treasury interest is assumed exempt from state tax in every state (a federal-law requirement); in-state municipal bond interest is assumed state-exempt and out-of-state municipal bond interest is assumed state-taxable -- a small number of states may vary from this general rule. State figures are simplified and some bracket thresholds are approximate -- see the notes column on the 'Tax Rates & Assumptions' tab for each state's specific assumptions, and verify current-year figures before precise client use. This tool does not cover realized capital gains or losses -- see the companion Capital Gains Tax Estimator for that. Always consult a qualified tax professional before making decisions based on this estimate. To update for a future tax year, edit the brackets and thresholds on the 'Tax Rates & Assumptions' tab -- no formulas on this tab need to change.
K54: CALCULATION DETAIL (reference only -- expand the outline to the left to audit the formulas behind every figure above)
K55: Filing category (Single/MFJ) | L55: =IF(F6="Married Filing Jointly","MFJ","Single") -> MFJ
K56: Federal key | L56: =C6&"|"&L55 -> 2025|MFJ
K57: Federal ordinary bracket row# | L57: =MATCH(L56,'Tax Rates & Assumptions'!C$6:C$1006,0) -> 4
K58: Qualified-dividend (LTCG-rate) bracket row# | L58: =MATCH(L56,'Tax Rates & Assumptions'!C$13:C$1013,0) -> 4
K59: Standard deduction row# | L59: =MATCH(L56,'Tax Rates & Assumptions'!C$20:C$1020,0) -> 4
K60: NIIT row# | L60: =MATCH(L55,'Tax Rates & Assumptions'!A$27:A$1027,0) -> 2
K61: State code | L61: =INDEX('Tax Rates & Assumptions'!A$33:A$1033,MATCH(I6,'Tax Rates & Assumptions'!B$33:B$1033,0)) -> NJ
K62: State master row# | L62: =MATCH(L61,'Tax Rates & Assumptions'!A$33:A$1033,0) -> 31
K63: State bracket key | L63: =L61&"|"&L55 -> NJ|MFJ
K64: State bracket row# | L64: =MATCH(L63,'Tax Rates & Assumptions'!C$87:C$1087,0) -> 62
K65: Standard deduction | L65: =INDEX('Tax Rates & Assumptions'!D$20:D$1020,L59) -> 30000
K66: NIIT MAGI threshold | L66: =INDEX('Tax Rates & Assumptions'!B$27:B$1027,L60) -> 250000
K67: NIIT rate | L67: =INDEX('Tax Rates & Assumptions'!C$27:C$1027,L60) -> 0.038
K68: State tax type | L68: =INDEX('Tax Rates & Assumptions'!C$33:C$1033,L62) -> Bracket
K69: State special mechanism | L69: =INDEX('Tax Rates & Assumptions'!E$33:E$1033,L62) -> 0
K70: Special param 1 | L70: =INDEX('Tax Rates & Assumptions'!F$33:F$1033,L62) -> 0
K71: Special param 2 | L71: =INDEX('Tax Rates & Assumptions'!G$33:G$1033,L62) -> 0
K72: Special param 3 | L72: =INDEX('Tax Rates & Assumptions'!H$33:H$1033,L62) -> 0
K73: State standard deduction | L73: =IF(L55="MFJ",INDEX('Tax Rates & Assumptions'!K$33:K$1033,L62),INDEX('Tax Rates & Assumptions'!J$33:J$1033,L62)) -> 0
K74: State description | L74: =INDEX('Tax Rates & Assumptions'!L$33:L$1033,L62) -> Progressive brackets (taxed as ordinary income)
K75: Federal Ordinary Brackets (staged)
L76: =INDEX('Tax Rates & Assumptions'!D$6:D$1006,L57) -> 0.1 | M76: =INDEX('Tax Rates & Assumptions'!E$6:E$1006,L57) -> 0 | N76: =INDEX('Tax Rates & Assumptions'!F$6:F$1006,L57) -> 23850
L77: =INDEX('Tax Rates & Assumptions'!G$6:G$1006,L57) -> 0.12 | M77: =INDEX('Tax Rates & Assumptions'!H$6:H$1006,L57) -> 23850 | N77: =INDEX('Tax Rates & Assumptions'!I$6:I$1006,L57) -> 96950
L78: =INDEX('Tax Rates & Assumptions'!J$6:J$1006,L57) -> 0.22 | M78: =INDEX('Tax Rates & Assumptions'!K$6:K$1006,L57) -> 96950 | N78: =INDEX('Tax Rates & Assumptions'!L$6:L$1006,L57) -> 206700
L79: =INDEX('Tax Rates & Assumptions'!M$6:M$1006,L57) -> 0.24 | M79: =INDEX('Tax Rates & Assumptions'!N$6:N$1006,L57) -> 206700 | N79: =INDEX('Tax Rates & Assumptions'!O$6:O$1006,L57) -> 394600
L80: =INDEX('Tax Rates & Assumptions'!P$6:P$1006,L57) -> 0.32 | M80: =INDEX('Tax Rates & Assumptions'!Q$6:Q$1006,L57) -> 394600 | N80: =INDEX('Tax Rates & Assumptions'!R$6:R$1006,L57) -> 501050
L81: =INDEX('Tax Rates & Assumptions'!S$6:S$1006,L57) -> 0.35 | M81: =INDEX('Tax Rates & Assumptions'!T$6:T$1006,L57) -> 501050 | N81: =INDEX('Tax Rates & Assumptions'!U$6:U$1006,L57) -> 751600
L82: =INDEX('Tax Rates & Assumptions'!V$6:V$1006,L57) -> 0.37 | M82: =INDEX('Tax Rates & Assumptions'!W$6:W$1006,L57) -> 751600 | N82: =INDEX('Tax Rates & Assumptions'!X$6:X$1006,L57) -> 999999999
K83: Qualified-Dividend (LTCG-rate) Brackets (staged)
L84: =INDEX('Tax Rates & Assumptions'!D$13:D$1013,L58) -> 0 | M84: =INDEX('Tax Rates & Assumptions'!E$13:E$1013,L58) -> 0 | N84: =INDEX('Tax Rates & Assumptions'!F$13:F$1013,L58) -> 96700
L85: =INDEX('Tax Rates & Assumptions'!G$13:G$1013,L58) -> 0.15 | M85: =INDEX('Tax Rates & Assumptions'!H$13:H$1013,L58) -> 96700 | N85: =INDEX('Tax Rates & Assumptions'!I$13:I$1013,L58) -> 600050
L86: =INDEX('Tax Rates & Assumptions'!J$13:J$1013,L58) -> 0.2 | M86: =INDEX('Tax Rates & Assumptions'!K$13:K$1013,L58) -> 600050 | N86: =INDEX('Tax Rates & Assumptions'!L$13:L$1013,L58) -> 999999999
K87: State Brackets (staged)
L88: =INDEX('Tax Rates & Assumptions'!D$87:D$1087,L64) -> 0.014 | M88: =INDEX('Tax Rates & Assumptions'!E$87:E$1087,L64) -> 0 | N88: =INDEX('Tax Rates & Assumptions'!F$87:F$1087,L64) -> 20000
L89: =INDEX('Tax Rates & Assumptions'!G$87:G$1087,L64) -> 0.0175 | M89: =INDEX('Tax Rates & Assumptions'!H$87:H$1087,L64) -> 20000 | N89: =INDEX('Tax Rates & Assumptions'!I$87:I$1087,L64) -> 50000
L90: =INDEX('Tax Rates & Assumptions'!J$87:J$1087,L64) -> 0.0245 | M90: =INDEX('Tax Rates & Assumptions'!K$87:K$1087,L64) -> 50000 | N90: =INDEX('Tax Rates & Assumptions'!L$87:L$1087,L64) -> 70000
L91: =INDEX('Tax Rates & Assumptions'!M$87:M$1087,L64) -> 0.035 | M91: =INDEX('Tax Rates & Assumptions'!N$87:N$1087,L64) -> 70000 | N91: =INDEX('Tax Rates & Assumptions'!O$87:O$1087,L64) -> 80000
L92: =INDEX('Tax Rates & Assumptions'!P$87:P$1087,L64) -> 0.05525 | M92: =INDEX('Tax Rates & Assumptions'!Q$87:Q$1087,L64) -> 80000 | N92: =INDEX('Tax Rates & Assumptions'!R$87:R$1087,L64) -> 150000
L93: =INDEX('Tax Rates & Assumptions'!S$87:S$1087,L64) -> 0.0637 | M93: =INDEX('Tax Rates & Assumptions'!T$87:T$1087,L64) -> 150000 | N93: =INDEX('Tax Rates & Assumptions'!U$87:U$1087,L64) -> 500000
L94: =INDEX('Tax Rates & Assumptions'!V$87:V$1087,L64) -> 0.0897 | M94: =INDEX('Tax Rates & Assumptions'!W$87:W$1087,L64) -> 500000 | N94: =INDEX('Tax Rates & Assumptions'!X$87:X$1087,L64) -> 1000000
L95: =INDEX('Tax Rates & Assumptions'!Y$87:Y$1087,L64) -> 0.1075 | M95: =INDEX('Tax Rates & Assumptions'!Z$87:Z$1087,L64) -> 1000000 | N95: =INDEX('Tax Rates & Assumptions'!AA$87:AA$1087,L64) -> 999999999
L96: =INDEX('Tax Rates & Assumptions'!AB$87:AB$1087,L64) -> 0 | M96: =INDEX('Tax Rates & Assumptions'!AC$87:AC$1087,L64) -> 999999999 | N96: =INDEX('Tax Rates & Assumptions'!AD$87:AD$1087,L64) -> 999999999
L97: =INDEX('Tax Rates & Assumptions'!AE$87:AE$1087,L64) -> 0 | M97: =INDEX('Tax Rates & Assumptions'!AF$87:AF$1087,L64) -> 999999999 | N97: =INDEX('Tax Rates & Assumptions'!AG$87:AG$1087,L64) -> 999999999
K98: Federal Tax Stacking
K99: Taxable income before portfolio income | L99: =MAX(0,C8-F8-L65) -> 160000
K100: Ordinary-taxed portfolio income (non-qual. div + taxable int. + Treasury int.) | L100: =(I8+F10+I10) -> 17000
K101: Taxable income after ordinary-taxed portfolio income | L101: =MAX(0,L99+L100) -> 177000
K102: Federal ordinary tax on income alone | L102: =SUMPRODUCT($L$76:$L$82*(($N$76:$N$82-($N$76:$N$82-L99)*(($N$76:$N$82-L99)>0))-$M$76:$M$82)*((($N$76:$N$82-($N$76:$N$82-L99)*(($N$76:$N$82-L99)>0))-$M$76:$M$82)>0)) -> 25028
K103: Federal ordinary tax including non-qualified dividends & interest | L103: =SUMPRODUCT($L$76:$L$82*(($N$76:$N$82-($N$76:$N$82-L101)*(($N$76:$N$82-L101)>0))-$M$76:$M$82)*((($N$76:$N$82-($N$76:$N$82-L101)*(($N$76:$N$82-L101)>0))-$M$76:$M$82)>0)) -> 28768
K104: Federal tax on non-qualified dividends & interest (ordinary rates) | L104: =(L103-L102) -> 3740
K105: Qualified-dividend bracket tax at the stacking point (before qualified dividends) | L105: =SUMPRODUCT($L$84:$L$86*(($N$84:$N$86-($N$84:$N$86-L101)*(($N$84:$N$86-L101)>0))-$M$84:$M$86)*((($N$84:$N$86-($N$84:$N$86-L101)*(($N$84:$N$86-L101)>0))-$M$84:$M$86)>0)) -> 12045
K106: Qualified-dividend bracket tax including qualified dividends | L106: =SUMPRODUCT($L$84:$L$86*(($N$84:$N$86-($N$84:$N$86-(L101+C10))*(($N$84:$N$86-(L101+C10))>0))-$M$84:$M$86)*((($N$84:$N$86-($N$84:$N$86-(L101+C10))*(($N$84:$N$86-(L101+C10))>0))-$M$84:$M$86)>0)) -> 14295
K107: Federal tax on qualified dividends (stacked 0%/15%/20%) | L107: =(L106-L105) -> 2250
K108: Net investment income (modeled dividends & interest; excludes tax-exempt muni interest) | L108: =L100+C10 -> 32000
K109: MAGI estimate | L109: =(L99+L65+L108) -> 222000
K110: Net Investment Income Tax (NIIT) | L110: =L67*MIN(L108,MAX(0,L109-L66)) -> 0
K111: Total estimated federal tax on the portfolio income | L111: =(L104+L107+L110) -> 5990
K112: State Tax
K113: State taxable income before the portfolio income | L113: =MAX(0,L99-L73) -> 160000
K114: State taxable income including all state-taxable portfolio income | L114: =MAX(0,L99+I8+F10+C10+F12-L73) -> 188000
K115: Generic state bracket tax on the portfolio income | L115: =SUMPRODUCT($L$88:$L$97*(($N$88:$N$97-($N$88:$N$97-L114)*(($N$88:$N$97-L114)>0))-$M$88:$M$97)*((($N$88:$N$97-($N$88:$N$97-L114)*(($N$88:$N$97-L114)>0))-$M$88:$M$97)>0))-SUMPRODUCT($L$88:$L$97*(($N$88:$N$97-($N$88:$N$97-L113)*(($N$88:$N$97-L113)>0))-$M$88:$M$97)*((($N$88:$N$97-($N$88:$N$97-L113)*(($N$88:$N$97-L113)>0))-$M$88:$M$97)>0)) -> 1783.6
K116: MA: state income including all state-taxable portfolio income | L116: =(L113+I8+F10+C10+F12) -> 188000
K117: MA: incremental 4% surtax caused by the portfolio income | L117: =(L72*MAX(0,L116-L71))-(L72*MAX(0,L113-L71)) -> 0
K118: MA total tax on the portfolio income (flat 5% + surtax, special) | L118: =L70*(I8+F10+C10+F12)+L117 -> 0
...

Sheet Tax Rates & Assumptions
A1: TAX RATES & ASSUMPTIONS
A2: This tab stores every tax-law figure used by the Dividend & Interest Income Tax Calculator (federal brackets, deduction amounts, thresholds, and all 50-state + DC treatment), organized by tax year. Update it to refresh figures for a new tax year -- no formulas on the Calculator tab need to change. Cells with a Notes column document simplifications/assumptions; verify flagged figures before precise client use.
A4: Federal Ordinary Income Tax Brackets
A5: Year | B5: Filing Status | C5: Key | D5: Rate 1 | E5: Min 1 | F5: Max 1 | G5: Rate 2 | H5: Min 2 | I5: Max 2 | J5: Rate 3 | K5: Min 3 | L5: Max 3 | M5: Rate 4 | N5: Min 4 | O5: Max 4 | P5: Rate 5 | Q5: Min 5 | R5: Max 5 | S5: Rate 6 | T5: Min 6 | U5: Max 6 | V5: Rate 7 | W5: Min 7 | X5: Max 7
A6: 2024 | B6: Single | C6: =A6&"|"&B6 -> 2024|Single | D6: 0.1 | E6: 0 | F6: =H6 -> 11600 | G6: 0.12 | H6: 11600 | I6: =K6 -> 47150 | J6: 0.22 | K6: 47150 | L6: =N6 -> 100525 | M6: 0.24 | N6: 100525 | O6: =Q6 -> 191950 | P6: 0.32 | Q6: 191950 | R6: =T6 -> 243725 | S6: 0.35 | T6: 243725 | U6: =W6 -> 609350 | V6: 0.37 | W6: 609350 | X6: 999999999
A7: 2024 | B7: MFJ | C7: =A7&"|"&B7 -> 2024|MFJ | D7: 0.1 | E7: 0 | F7: =H7 -> 23200 | G7: 0.12 | H7: 23200 | I7: =K7 -> 94300 | J7: 0.22 | K7: 94300 | L7: =N7 -> 201050 | M7: 0.24 | N7: 201050 | O7: =Q7 -> 383900 | P7: 0.32 | Q7: 383900 | R7: =T7 -> 487450 | S7: 0.35 | T7: 487450 | U7: =W7 -> 731200 | V7: 0.37 | W7: 731200 | X7: 999999999
A8: 2025 | B8: Single | C8: =A8&"|"&B8 -> 2025|Single | D8: 0.1 | E8: 0 | F8: =H8 -> 11925 | G8: 0.12 | H8: 11925 | I8: =K8 -> 48475 | J8: 0.22 | K8: 48475 | L8: =N8 -> 103350 | M8: 0.24 | N8: 103350 | O8: =Q8 -> 197300 | P8: 0.32 | Q8: 197300 | R8: =T8 -> 250525 | S8: 0.35 | T8: 250525 | U8: =W8 -> 626350 | V8: 0.37 | W8: 626350 | X8: 999999999
A9: 2025 | B9: MFJ | C9: =A9&"|"&B9 -> 2025|MFJ | D9: 0.1 | E9: 0 | F9: =H9 -> 23850 | G9: 0.12 | H9: 23850 | I9: =K9 -> 96950 | J9: 0.22 | K9: 96950 | L9: =N9 -> 206700 | M9: 0.24 | N9: 206700 | O9: =Q9 -> 394600 | P9: 0.32 | Q9: 394600 | R9: =T9 -> 501050 | S9: 0.35 | T9: 501050 | U9: =W9 -> 751600 | V9: 0.37 | W9: 751600 | X9: 999999999
A11: Federal Qualified Dividend / LTCG-Rate Brackets (0% / 15% / 20%)
A12: Year | B12: Filing Status | C12: Key | D12: Rate 1 | E12: Min 1 | F12: Max 1 | G12: Rate 2 | H12: Min 2 | I12: Max 2 | J12: Rate 3 | K12: Min 3 | L12: Max 3
A13: 2024 | B13: Single | C13: =A13&"|"&B13 -> 2024|Single | D13: 0 | E13: 0 | F13: =H13 -> 47025 | G13: 0.15 | H13: 47025 | I13: =K13 -> 518900 | J13: 0.2 | K13: 518900 | L13: 999999999
A14: 2024 | B14: MFJ | C14: =A14&"|"&B14 -> 2024|MFJ | D14: 0 | E14: 0 | F14: =H14 -> 94050 | G14: 0.15 | H14: 94050 | I14: =K14 -> 583750 | J14: 0.2 | K14: 583750 | L14: 999999999
A15: 2025 | B15: Single | C15: =A15&"|"&B15 -> 2025|Single | D15: 0 | E15: 0 | F15: =H15 -> 48350 | G15: 0.15 | H15: 48350 | I15: =K15 -> 533400 | J15: 0.2 | K15: 533400 | L15: 999999999
A16: 2025 | B16: MFJ | C16: =A16&"|"&B16 -> 2025|MFJ | D16: 0 | E16: 0 | F16: =H16 -> 96700 | G16: 0.15 | H16: 96700 | I16: =K16 -> 600050 | J16: 0.2 | K16: 600050 | L16: 999999999
A18: Federal Standard Deduction
A19: Year | B19: Filing Status | C19: Key | D19: Standard Deduction
A20: 2024 | B20: Single | C20: =A20&"|"&B20 -> 2024|Single | D20: 14600
A21: 2024 | B21: MFJ | C21: =A21&"|"&B21 -> 2024|MFJ | D21: 29200
A22: 2025 | B22: Single | C22: =A22&"|"&B22 -> 2025|Single | D22: 15000
A23: 2025 | B23: MFJ | C23: =A23&"|"&B23 -> 2025|MFJ | D23: 30000
A25: NIIT Thresholds & Rate (fixed by statute)
A26: Filing Status | B26: NIIT MAGI Threshold | C26: NIIT Rate
A27: Single | B27: 200000 | C27: 0.038
A28: MFJ | B28: 250000 | C28: 0.038
A31: State Master List & Interest/Dividend Tax Treatment (all 50 states + DC)
A32: State Code | B32: State Name | C32: Tax Type | D32: Flat Rate | E32: Special Mechanism | F32: Special Param 1 | G32: Special Param 2 | H32: Special Param 3 | I32: Special Param 4 | J32: Std. Deduction (Single) | K32: Std. Deduction (MFJ) | L32: Client-Facing Description | M32: Notes / Assumptions / Vintage
A33: AL | B33: Alabama | C33: Bracket | D33: 0 | F33: 0 | G33: 0 | H33: 0 | I33: 0 | J33: 0 | K33: 0 | L33: Progressive brackets (taxed as ordinary income) | M33: Graduated brackets, but thresholds are so low most filers effectively pay the 5% top rate.
A34: AK | B34: Alaska | C34: None | D34: 0 | F34: 0 | G34: 0 | H34: 0 | I34: 0 | J34: 0 | K34: 0 | L34: No state income tax | M34: No individual income tax; interest and dividends are not taxed.
A35: AZ | B35: Arizona | C35: Flat | D35: 0.025 | F35: 0 | G35: 0 | H35: 0 | I35: 0 | J35: 14600 | K35: 29200 | L35: Flat 2.50% | M35: Flat-rate state; 2.50% applies to all taxable income including interest and dividends. 2025 rate.
A36: AR | B36: Arkansas | C36: Bracket | D36: 0 | F36: 0 | G36: 0 | H36: 0 | I36: 0 | J36: 0 | K36: 0 | L36: Progressive brackets (taxed as ordinary income) | M36: Graduated brackets (same schedule for all filing statuses; simplified/approximate). (Arkansas's 50% capital-gains exclusion does not apply to interest or dividends.)
A37: CA | B37: California | C37: Bracket | D37: 0 | F37: 0 | G37: 0 | H37: 0 | I37: 0 | J37: 5540 | K37: 11080 | L37: Progressive brackets (taxed as ordinary income) | M37: Progressive brackets; includes the 1% Mental Health Services surcharge on income over $1,000,000.
A38: CO | B38: Colorado | C38: Flat | D38: 0.0425 | F38: 0 | G38: 0 | H38: 0 | I38: 0 | J38: 0 | K38: 0 | L38: Flat 4.25% | M38: Flat-rate state; 4.25% applies to all taxable income including interest and dividends. 2025 rate.
A39: CT | B39: Connecticut | C39: Bracket | D39: 0 | F39: 0 | G39: 0 | H39: 0 | I39: 0 | J39: 0 | K39: 0 | L39: Progressive brackets (taxed as ordinary income) | M39: Progressive brackets. Connecticut's benefit-recapture provision for high earners is not modeled.
A40: DE | B40: Delaware | C40: Bracket | D40: 0 | F40: 0 | G40: 0 | H40: 0 | I40: 0 | J40: 0 | K40: 0 | L40: Progressive brackets (taxed as ordinary income) | M40: Progressive brackets (same schedule for all filing statuses).
A41: DC | B41: District of Columbia | C41: Bracket | D41: 0 | F41: 0 | G41: 0 | H41: 0 | I41: 0 | J41: 14600 | K41: 29200 | L41: Progressive brackets (taxed as ordinary income) | M41: Progressive brackets (same schedule for all filing statuses).
A42: FL | B42: Florida | C42: None | D42: 0 | F42: 0 | G42: 0 | H42: 0 | I42: 0 | J42: 0 | K42: 0 | L42: No state income tax | M42: No individual income tax; interest and dividends are not taxed.
A43: GA | B43: Georgia | C43: Flat | D43: 0.0519 | F43: 0 | G43: 0 | H43: 0 | I43: 0 | J43: 12000 | K43: 24000 | L43: Flat 5.19% | M43: Flat-rate state; 5.19% applies to all taxable income including interest and dividends. 2025 rate.
A44: HI | B44: Hawaii | C44: Bracket | D44: 0 | F44: 0 | G44: 0 | H44: 0 | I44: 0 | J44: 2200 | K44: 4400 | L44: Progressive brackets (taxed as ordinary income) | M44: Progressive brackets up to 11%. (Hawaii's 7.25% preferential rate applies only to long-term capital gains, not to interest or dividends.) Middle bracket thresholds are approximate -- verify against HI DOTAX.
... A53: MD | B53: Maryland | C53: Bracket | D53: 0 | F53: 0 | G53: 0 | H53: 0 | I53: 0 | J53: 2400 | K53: 4850 | L53: Progressive brackets (taxed as ordinary income) | M53: Progressive brackets (includes the 6.25%/6.5% top brackets added for 2025). Excludes county/city 'piggyback' local income tax (2.25%-3.20%) -- actual total MD tax will be higher than shown.
A54: MA | B54: Massachusetts | C54: Special | D54: 0 | E54: MA_FLAT | F54: 0.05 | G54: 1083150 | H54: 0.04 | I54: 0 | J54: 0 | K54: 0 | L54: Flat 5% (plus 4% surtax over $1,083,150) -- no qualified-dividend preference | M54: Flat tax. Massachusetts does NOT give qualified dividends any preferential rate -- all interest and dividends (qualified or not) are taxed at a flat 5%, plus a 4% surtax on all income above $1,083,150 (2025).
A55: MI | B55: Michigan | C55: Flat | D55: 0.0425 | F55: 0 | G55: 0 | H55: 0 | I55: 0 | J55: 0 | K55: 0 | L55: Flat 4.25% | M55: Flat-rate state; 4.25% applies to all taxable income including interest and dividends. 2025 rate.
A56: MN | B56: Minnesota | C56: Bracket | D56: 0 | F56: 0 | G56: 0 | H56: 0 | I56: 0 | J56: 14575 | K56: 29150 | L56: Progressive brackets (taxed as ordinary income) | M56: Progressive brackets.
A57: MS | B57: Mississippi | C57: Flat | D57: 0.044 | F57: 0 | G57: 0 | H57: 0 | I57: 0 | J57: 0 | K57: 0 | L57: Flat 4.40% | M57: Flat-rate state; 4.40% applies to all taxable income including interest and dividends. 2025 rate.
A58: MO | B58: Missouri | C58: Bracket | D58: 0 | F58: 0 | G58: 0 | H58: 0 | I58: 0 | J58: 0 | K58: 0 | L58: Progressive brackets (taxed as ordinary income) | M58: Progressive brackets (same schedule for all filing statuses).
A59: MT | B59: Montana | C59: Bracket | D59: 0 | F59: 0 | G59: 0 | H59: 0 | I59: 0 | J59: 0 | K59: 0 | L59: Progressive brackets (taxed as ordinary income) | M59: Two-bracket structure. (Montana's lower 3.0%/4.1% rate schedule applies only to long-term capital gains, not to interest or dividends.)
A60: NE | B60: Nebraska | C60: Bracket | D60: 0 | F60: 0 | G60: 0 | H60: 0 | I60: 0 | J60: 0 | K60: 0 | L60: Progressive brackets (taxed as ordinary income) | M60: Progressive brackets (middle thresholds approximate).
A61: NV | B61: Nevada | C61: None | D61: 0 | F61: 0 | G61: 0 | H61: 0 | I61: 0 | J61: 0 | K61: 0 | L61: No state income tax | M61: No individual income tax; interest and dividends are not taxed.
A62: NH | B62: New Hampshire | C62: None | D62: 0 | F62: 0 | G62: 0 | H62: 0 | I62: 0 | J62: 0 | K62: 0 | L62: No state income tax | M62: No individual income tax; interest and dividends are not taxed.
A63: NJ | B63: New Jersey | C63: Bracket | D63: 0 | F63: 0 | G63: 0 | H63: 0 | I63: 0 | J63: 0 | K63: 0 | L63: Progressive brackets (taxed as ordinary income) | M63: Progressive brackets. Top-bracket thresholds are not doubled for joint filers.
A64: NM | B64: New Mexico | C64: Bracket | D64: 0 | F64: 0 | G64: 0 | H64: 0 | I64: 0 | J64: 0 | K64: 0 | L64: Progressive brackets (taxed as ordinary income) | M64: Progressive brackets (approximate -- verify against NM TRD).
A65: NY | B65: New York | C65: Bracket | D65: 0 | F65: 0 | G65: 0 | H65: 0 | I65: 0 | J65: 8000 | K65: 16050 | L65: Progressive brackets (taxed as ordinary income) | M65: Progressive brackets. NYC/local tax not modeled.
A66: NC | B66: North Carolina | C66: Flat | D66: 0.0425 | F66: 0 | G66: 0 | H66: 0 | I66: 0 | J66: 12750 | K66: 25500 | L66: Flat 4.25% | M66: Flat-rate state; 4.25% applies to all taxable income including interest and dividends. 2025 rate.
... A83: WY | B83: Wyoming | C83: None | D83: 0 | F83: 0 | G83: 0 | H83: 0 | I83: 0 | J83: 0 | K83: 0 | L83: No state income tax | M83: No individual income tax; interest and dividends are not taxed.
A85: State Income Tax Brackets (unified format; up to 10 tiers; Flat/None states use a single degenerate tier)
A86: State Code | B86: Filing Category | C86: Key | D86: Rate 1 | E86: Min 1 | F86: Max 1 | G86: Rate 2 | H86: Min 2 | I86: Max 2 | J86: Rate 3 | K86: Min 3 | L86: Max 3 | M86: Rate 4 | N86: Min 4 | O86: Max 4 | P86: Rate 5 | Q86: Min 5 | R86: Max 5 | S86: Rate 6 | T86: Min 6 | U86: Max 6 | V86: Rate 7 | W86: Min 7 | X86: Max 7 | Y86: Rate 8 | Z86: Min 8 | AA86: Max 8 | AB86: Rate 9 | AC86: Min 9 | AD86: Max 9 | AE86: Rate 10 | AF86: Min 10 | AG86: Max 10
A87: AL | B87: Single | C87: =A87&"|"&B87 -> AL|Single | D87: 0.02 | E87: 0 | F87: =H87 -> 500 | G87: 0.04 | H87: 500 | I87: =K87 -> 3000 | J87: 0.05 | K87: 3000 | L87: =N87 -> 999999999 | M87: 0 | N87: 999999999 | O87: =Q87 -> 999999999 | P87: 0 | Q87: 999999999 | R87: =T87 -> 999999999 | S87: 0 | T87: 999999999 | U87: =W87 -> 999999999 | V87: 0 | W87: 999999999 | X87: =Z87 -> 999999999 | Y87: 0 | Z87: 999999999 | AA87: =AC87 -> 999999999 | AB87: 0 | AC87: 999999999 | AD87: =AF87 -> 999999999 | AE87: 0 | AF87: 999999999 | AG87: 999999999
A88: AL | B88: MFJ | C88: =A88&"|"&B88 -> AL|MFJ | D88: 0.02 | E88: 0 | F88: =H88 -> 1000 | G88: 0.04 | H88: 1000 | I88: =K88 -> 6000 | J88: 0.05 | K88: 6000 | L88: =N88 -> 999999999 | M88: 0 | N88: 999999999 | O88: =Q88 -> 999999999 | P88: 0 | Q88: 999999999 | R88: =T88 -> 999999999 | S88: 0 | T88: 999999999 | U88: =W88 -> 999999999 | V88: 0 | W88: 999999999 | X88: =Z88 -> 999999999 | Y88: 0 | Z88: 999999999 | AA88: =AC88 -> 999999999 | AB88: 0 | AC88: 999999999 | AD88: =AF88 -> 999999999 | AE88: 0 | AF88: 999999999 | AG88: 999999999
A89: AK | B89: Single | C89: =A89&"|"&B89 -> AK|Single | D89: 0 | E89: 0 | F89: =H89 -> 999999999 | G89: 0 | H89: 999999999 | I89: =K89 -> 999999999 | J89: 0 | K89: 999999999 | L89: =N89 -> 999999999 | M89: 0 | N89: 999999999 | O89: =Q89 -> 999999999 | P89: 0 | Q89: 999999999 | R89: =T89 -> 999999999 | S89: 0 | T89: 999999999 | U89: =W89 -> 999999999 | V89: 0 | W89: 999999999 | X89: =Z89 -> 999999999 | Y89: 0 | Z89: 999999999 | AA89: =AC89 -> 999999999 | AB89: 0 | AC89: 999999999 | AD89: =AF89 -> 999999999 | AE89: 0 | AF89: 999999999 | AG89: 999999999
A90: AK | B90: MFJ | C90: =A90&"|"&B90 -> AK|MFJ | D90: 0 | E90: 0 | F90: =H90 -> 999999999 | G90: 0 | H90: 999999999 | I90: =K90 -> 999999999 | J90: 0 | K90: 999999999 | L90: =N90 -> 999999999 | M90: 0 | N90: 999999999 | O90: =Q90 -> 999999999 | P90: 0 | Q90: 999999999 | R90: =T90 -> 999999999 | S90: 0 | T90: 999999999 | U90: =W90 -> 999999999 | V90: 0 | W90: 999999999 | X90: =Z90 -> 999999999 | Y90: 0 | Z90: 999999999 | AA90: =AC90 -> 999999999 | AB90: 0 | AC90: 999999999 | AD90: =AF90 -> 999999999 | AE90: 0 | AF90: 999999999 | AG90: 999999999
A91: AZ | B91: Single | C91: =A91&"|"&B91 -> AZ|Single | D91: 0.025 | E91: 0 | F91: =H91 -> 999999999 | G91: 0 | H91: 999999999 | I91: =K91 -> 999999999 | J91: 0 | K91: 999999999 | L91: =N91 -> 999999999 | M91: 0 | N91: 999999999 | O91: =Q91 -> 999999999 | P91: 0 | Q91: 999999999 | R91: =T91 -> 999999999 | S91: 0 | T91: 999999999 | U91: =W91 -> 999999999 | V91: 0 | W91: 999999999 | X91: =Z91 -> 999999999 | Y91: 0 | Z91: 999999999 | AA91: =AC91 -> 999999999 | AB91: 0 | AC91: 999999999 | AD91: =AF91 -> 999999999 | AE91: 0 | AF91: 999999999 | AG91: 999999999
A92: AZ | B92: MFJ | C92: =A92&"|"&B92 -> AZ|MFJ | D92: 0.025 | E92: 0 | F92: =H92 -> 999999999 | G92: 0 | H92: 999999999 | I92: =K92 -> 999999999 | J92: 0 | K92: 999999999 | L92: =N92 -> 999999999 | M92: 0 | N92: 999999999 | O92: =Q92 -> 999999999 | P92: 0 | Q92: 999999999 | R92: =T92 -> 999999999 | S92: 0 | T92: 999999999 | U92: =W92 -> 999999999 | V92: 0 | W92: 999999999 | X92: =Z92 -> 999999999 | Y92: 0 | Z92: 999999999 | AA92: =AC92 -> 999999999 | AB92: 0 | AC92: 999999999 | AD92: =AF92 -> 999999999 | AE92: 0 | AF92: 999999999 | AG92: 999999999
A93: AR | B93: Single | C93: =A93&"|"&B93 -> AR|Single | D93: 0 | E93: 0 | F93: =H93 -> 5100 | G93: 0.02 | H93: 5100 | I93: =K93 -> 10600 | J93: 0.039 | K93: 10600 | L93: =N93 -> 999999999 | M93: 0 | N93: 999999999 | O93: =Q93 -> 999999999 | P93: 0 | Q93: 999999999 | R93: =T93 -> 999999999 | S93: 0 | T93: 999999999 | U93: =W93 -> 999999999 | V93: 0 | W93: 999999999 | X93: =Z93 -> 999999999 | Y93: 0 | Z93: 999999999 | AA93: =AC93 -> 999999999 | AB93: 0 | AC93: 999999999 | AD93: =AF93 -> 999999999 | AE93: 0 | AF93: 999999999 | AG93: 999999999
A94: AR | B94: MFJ | C94: =A94&"|"&B94 -> AR|MFJ | D94: 0 | E94: 0 | F94: =H94 -> 5100 | G94: 0.02 | H94: 5100 | I94: =K94 -> 10600 | J94: 0.039 | K94: 10600 | L94: =N94 -> 999999999 | M94: 0 | N94: 999999999 | O94: =Q94 -> 999999999 | P94: 0 | Q94: 999999999 | R94: =T94 -> 999999999 | S94: 0 | T94: 999999999 | U94: =W94 -> 999999999 | V94: 0 | W94: 999999999 | X94: =Z94 -> 999999999 | Y94: 0 | Z94: 999999999 | AA94: =AC94 -> 999999999 | AB94: 0 | AC94: 999999999 | AD94: =AF94 -> 999999999 | AE94: 0 | AF94: 999999999 | AG94: 999999999
A95: CA | B95: Single | C95: =A95&"|"&B95 -> CA|Single | D95: 0.01 | E95: 0 | F95: =H95 -> 11079 | G95: 0.02 | H95: 11079 | I95: =K95 -> 26264 | J95: 0.04 | K95: 26264 | L95: =N95 -> 41452 | M95: 0.06 | N95: 41452 | O95: =Q95 -> 57542 | P95: 0.08 | Q95: 57542 | R95: =T95 -> 72724 | S95: 0.093 | T95: 72724 | U95: =W95 -> 371479 | V95: 0.103 | W95: 371479 | X95: =Z95 -> 445771 | Y95: 0.113 | Z95: 445771 | AA95: =AC95 -> 742953 | AB95: 0.123 | AC95: 742953 | AD95: =AF95 -> 1000000 | AE95: 0.133 | AF95: 1000000 | AG95: 999999999
A96: CA | B96: MFJ | C96: =A96&"|"&B96 -> CA|MFJ | D96: 0.01 | E96: 0 | F96: =H96 -> 22158 | G96: 0.02 | H96: 22158 | I96: =K96 -> 52528 | J96: 0.04 | K96: 52528 | L96: =N96 -> 82904 | M96: 0.06 | N96: 82904 | O96: =Q96 -> 115084 | P96: 0.08 | Q96: 115084 | R96: =T96 -> 145448 | S96: 0.093 | T96: 145448 | U96: =W96 -> 742958 | V96: 0.103 | W96: 742958 | X96: =Z96 -> 891542 | Y96: 0.113 | Z96: 891542 | AA96: =AC96 -> 1000000 | AB96: 0.123 | AC96: 1000000 | AD96: =AF96 -> 1485906 | AE96: 0.133 | AF96: 1485906 | AG96: 999999999
A97: CO | B97: Single | C97: =A97&"|"&B97 -> CO|Single | D97: 0.0425 | E97: 0 | F97: =H97 -> 999999999 | G97: 0 | H97: 999999999 | I97: =K97 -> 999999999 | J97: 0 | K97: 999999999 | L97: =N97 -> 999999999 | M97: 0 | N97: 999999999 | O97: =Q97 -> 999999999 | P97: 0 | Q97: 999999999 | R97: =T97 -> 999999999 | S97: 0 | T97: 999999999 | U97: =W97 -> 999999999 | V97: 0 | W97: 999999999 | X97: =Z97 -> 999999999 | Y97: 0 | Z97: 999999999 | AA97: =AC97 -> 999999999 | AB97: 0 | AC97: 999999999 | AD97: =AF97 -> 999999999 | AE97: 0 | AF97: 999999999 | AG97: 999999999
A98: CO | B98: MFJ | C98: =A98&"|"&B98 -> CO|MFJ | D98: 0.0425 | E98: 0 | F98: =H98 -> 999999999 | G98: 0 | H98: 999999999 | I98: =K98 -> 999999999 | J98: 0 | K98: 999999999 | L98: =N98 -> 999999999 | M98: 0 | N98: 999999999 | O98: =Q98 -> 999999999 | P98: 0 | Q98: 999999999 | R98: =T98 -> 999999999 | S98: 0 | T98: 999999999 | U98: =W98 -> 999999999 | V98: 0 | W98: 999999999 | X98: =Z98 -> 999999999 | Y98: 0 | Z98: 999999999 | AA98: =AC98 -> 999999999 | AB98: 0 | AC98: 999999999 | AD98: =AF98 -> 999999999 | AE98: 0 | AF98: 999999999 | AG98: 999999999
... A188: WY | B188: MFJ | C188: =A188&"|"&B188 -> WY|MFJ | D188: 0 | E188: 0 | F188: =H188 -> 999999999 | G188: 0 | H188: 999999999 | I188: =K188 -> 999999999 | J188: 0 | K188: 999999999 | L188: =N188 -> 999999999 | M188: 0 | N188: 999999999 | O188: =Q188 -> 999999999 | P188: 0 | Q188: 999999999 | R188: =T188 -> 999999999 | S188: 0 | T188: 999999999 | U188: =W188 -> 999999999 | V188: 0 | W188: 999999999 | X188: =Z188 -> 999999999 | Y188: 0 | Z188: 999999999 | AA188: =AC188 -> 999999999 | AB188: 0 | AC188: 999999999 | AD188: =AF188 -> 999999999 | AE188: 0 | AF188: 999999999 | AG188: 999999999
