Workbook

Sheet Client Input
B1: Dividend / Portfolio Income / Interest Tax Estimator
B2: Federal & New Jersey estimate for NJ residents — enter the client's data in the yellow cells. Results appear on the Client Summary tab.
B3: Legend: | C3: Input (edit) | D3: Formula (protected) | E3: Tax assumptions live on the 'Tax Tables & Assumptions' tab
B5: Item | C5: Value | D5: Check | E5: Notes
B6: CLIENT INFORMATION
B7: Client name | C7: Sample Client (replace) | D7: =IF(TRIM(C7)="","MISSING – required","OK") -> OK | E7: Required.
B8: Tax year | C8: 2026 | D8: =IF(C8="","MISSING – required",IF(C8<>'Tax Tables & Assumptions'!$C$3,"WARNING – tax tables are for "&'Tax Tables & Assumptions'!$C$3,"OK")) -> OK | E8: Required. Must match the year of the Tax Tables tab.
B9: Filing status | C9: Married Filing Jointly | D9: =IF(C9="","MISSING – required",IF(ISNA(MATCH(C9,'Tax Tables & Assumptions'!$D$7:$G$7,0)),"ERROR – choose from list","OK")) -> OK | E9: Required. Dropdown: Single, MFJ, MFS, Head of Household.
B10: New Jersey resident? | C10: Yes | D10: =IF(C10="","MISSING – required",IF(C10="No","WARNING – NJ tax set to $0 (non-resident)","OK")) -> OK | E10: Required. Yes/No. The NJ calculation applies to full-year NJ residents.
B11: Number of dependents (for NJ $1,500 exemptions) – optional | C11: 0 | D11: =IF(C11="","OK (blank = 0)",IF(NOT(ISNUMBER(C11)),"ERROR – must be a number",IF(OR(C11<0,C11<>INT(C11)),"ERROR – whole number ≥ 0","OK"))) -> OK | E11: Optional. Used only for NJ exemptions.
B13: EXISTING INCOME (BEFORE INVESTMENT INCOME)
B14: Estimated ordinary taxable income BEFORE investment income | C14: 150000 | D14: =IF(C14="","MISSING – required (enter 0 if none)",IF(NOT(ISNUMBER(C14)),"ERROR – must be a number",IF(C14<0,"ERROR – cannot be negative","OK"))) -> OK | E14: Required. Federal TAXABLE income (after deductions) from wages, pensions, business income, etc. — EXCLUDING the investment income entered below.
B15: Federal deduction assumed (optional – blank = standard deduction) | D15: =IF(C15="","OK (blank = standard deduction)",IF(NOT(ISNUMBER(C15)),"ERROR – must be a number",IF(C15<0,"ERROR – cannot be negative","OK"))) -> OK (blank = standard deduction) | E15: Optional. Enter itemized deductions if the client itemizes. Used to estimate AGI/MAGI (NIIT) and NJ income.
B16: NJ taxable income BEFORE investment income (optional override) | D16: =IF(C16="","OK (blank = estimated automatically)",IF(NOT(ISNUMBER(C16)),"ERROR – must be a number",IF(C16<0,"ERROR – cannot be negative","OK"))) -> OK (blank = estimated automatically) | E16: Optional. NJ income after NJ exemptions, excluding investment income. Blank = federal taxable income + federal deduction − NJ exemptions.
B18: INVESTMENT INCOME (ANNUAL AMOUNTS)
B19: Qualified dividends | C19: 20000 | D19: =IF(C19="","OK (blank = $0)",IF(NOT(ISNUMBER(C19)),"ERROR – must be a number",IF(C19<0,"ERROR – cannot be negative","OK"))) -> OK | E19: Federal: 0/15/20% rates. NJ: taxable at ordinary NJ rates.
B20: Ordinary / non-qualified dividends | C20: 5000 | D20: =IF(C20="","OK (blank = $0)",IF(NOT(ISNUMBER(C20)),"ERROR – must be a number",IF(C20<0,"ERROR – cannot be negative","OK"))) -> OK | E20: Do NOT include qualified dividends here. Federal & NJ: ordinary.
B21: Money market income | C21: 5000 | D21: =IF(C21="","OK (blank = $0)",IF(NOT(ISNUMBER(C21)),"ERROR – must be a number",IF(C21<0,"ERROR – cannot be negative","OK"))) -> OK | E21: Federal: ordinary. NJ: taxable except the exempt % entered below.
B22: Bank / CD interest | C22: 10000 | D22: =IF(C22="","OK (blank = $0)",IF(NOT(ISNUMBER(C22)),"ERROR – must be a number",IF(C22<0,"ERROR – cannot be negative","OK"))) -> OK | E22: Federal & NJ: ordinary.
B23: Other taxable interest (corporate bonds, etc.) | C23: 0 | D23: =IF(C23="","OK (blank = $0)",IF(NOT(ISNUMBER(C23)),"ERROR – must be a number",IF(C23<0,"ERROR – cannot be negative","OK"))) -> OK | E23: Federal & NJ: ordinary.
B24: U.S. Treasury interest (bills, notes, bonds, I/EE bonds) | C24: 0 | D24: =IF(C24="","OK (blank = $0)",IF(NOT(ISNUMBER(C24)),"ERROR – must be a number",IF(C24<0,"ERROR – cannot be negative","OK"))) -> OK | E24: Federal: ordinary. NJ: EXEMPT (U.S. government obligation).
B25: Tax-exempt / municipal interest | C25: 0 | D25: =IF(C25="","OK (blank = $0)",IF(NOT(ISNUMBER(C25)),"ERROR – must be a number",IF(C25<0,"ERROR – cannot be negative","OK"))) -> OK | E25: Federal: exempt. NJ: exempt if from NJ issuers; out-of-state munis are NJ taxable (see % below).
B26: Short-term capital gains (net, held ≤ 1 year) | C26: 0 | D26: =IF(C26="","OK (blank = $0)",IF(NOT(ISNUMBER(C26)),"ERROR – must be a number",IF(C26<0,"ERROR – cannot be negative","OK"))) -> OK | E26: Federal: ordinary rates. NJ: taxable. Enter ≥ 0.
B27: Long-term capital gains (net, held > 1 year) | C27: 10000 | D27: =IF(C27="","OK (blank = $0)",IF(NOT(ISNUMBER(C27)),"ERROR – must be a number",IF(C27<0,"ERROR – cannot be negative","OK"))) -> OK | E27: Federal: 0/15/20% rates. NJ: taxable. Enter ≥ 0.
B29: NEW JERSEY TREATMENT ADJUSTMENTS
B30: Money market: % from U.S. obligations that is NJ-exempt | C30: 0 | D30: =IF(C30="","OK (blank = 0%)",IF(NOT(ISNUMBER(C30)),"ERROR – must be a %",IF(OR(C30<0,C30>1),"ERROR – must be 0% to 100%","OK"))) -> OK | E30: Only if the fund is a NJ 'qualified investment fund' (fund's year-end NJ tax letter). Otherwise 0%.
B31: Municipal interest: % from New Jersey issuers (NJ-exempt) | C31: 1 | D31: =IF(C31="","OK (blank = 0% NJ issuers)",IF(NOT(ISNUMBER(C31)),"ERROR – must be a %",IF(OR(C31<0,C31>1),"ERROR – must be 0% to 100%","OK"))) -> OK | E31: 100% = all NJ bonds (NJ-exempt). 0% = all out-of-state bonds (taxable in NJ). National muni funds publish the NJ %.
B33: CALCULATED TOTALS (formulas – protected)
B34: Total ordinary investment income (non-qualified dividends + all taxable interest, incl. Treasury) | C34: =SUM(C20:C24) -> 20000 | E34: Taxed federally at ordinary rates.
B35: Total qualified dividends | C35: =C19 -> 20000 | E35: Federal preferential rates.
B36: Total short-term capital gains | C36: =C26 -> 0 | E36: Taxed federally as ordinary income.
B37: Total long-term capital gains | C37: =C27 -> 10000 | E37: Federal preferential rates.
B38: Total federally taxable investment income | C38: =C34+C35+C36+C37 -> 50000 | E38: Also = net investment income for NIIT.
B39: Total tax-exempt income (municipal interest) | C39: =C25 -> 0 | E39: Federally exempt.
B40: TOTAL INVESTMENT INCOME (all sources) | C40: =C38+C39 -> 50000 | D40: =IF(C40=0,"WARNING – no investment income entered","OK") -> OK | E40: Taxable + tax-exempt.
B42: INPUT STATUS: | C42: =IF(COUNTIF(D7:D40,"ERROR*")>0,"⚠ INPUT ERRORS – correct the cells flagged in column D",IF(COUNTIF(D7:D40,"MISSING*")>0,"⚠ REQUIRED INFORMATION MISSING – see column D",IF(COUNTIF(D7:D40,"WARNING*")>0,"✓ Complete, with warnings (column D) – results are ESTIMATES","✓ Inputs complete – results are ESTIMATES only"))) -> ✓ Inputs complete – results are ESTIMATES only
B44: All results are high-level planning ESTIMATES, not tax preparation. Sheets are protected without a password (Review ▸ Unprotect Sheet) to prevent accidental edits to formulas.

Sheet Tax Calculation
B1: Tax Calculation (all formulas – protected)
B2: Green = linked from another tab · Black = calculated here. Marginal method: tax WITH investment income minus tax WITHOUT it.
B4: A. CLIENT PARAMETERS & ASSUMPTIONS SELECTED FOR THIS FILING STATUS
B5: Filing status (index 1–4 into tax tables) | C5: =IFERROR(MATCH('Client Input'!$C$9,'Tax Tables & Assumptions'!$D$7:$G$7,0),1) -> 2 | D5: 1=Single, 2=MFJ, 3=MFS, 4=HoH (defaults to 1 if blank).
B6: NJ resident flag (1 = Yes) | C6: =IF('Client Input'!$C$10="No",0,1) -> 1 | D6: Blank is treated as Yes; a warning shows on Client Input.
B7: Federal standard deduction | C7: =INDEX('Tax Tables & Assumptions'!$D$18:$G$18,$C$5) -> 32200
B8: Federal deduction assumed | C8: =IF('Client Input'!$C$15="",C7,MAX(0,'Client Input'!$C$15)) -> 32200 | D8: Standard deduction unless overridden on Client Input.
B9: QD/LTCG 15% tier begins above (taxable income) | C9: =INDEX('Tax Tables & Assumptions'!$D$23:$G$23,$C$5) -> 98900
B10: QD/LTCG 20% tier begins above (taxable income) | C10: =INDEX('Tax Tables & Assumptions'!$D$24:$G$24,$C$5) -> 613700
B11: QD/LTCG rate – 0% tier | C11: ='Tax Tables & Assumptions'!$C$22 -> 0
B12: QD/LTCG rate – 15% tier | C12: ='Tax Tables & Assumptions'!$C$23 -> 0.15
B13: QD/LTCG rate – 20% tier | C13: ='Tax Tables & Assumptions'!$C$24 -> 0.2
B14: NIIT rate | C14: ='Tax Tables & Assumptions'!$C$28 -> 0.038
B15: NIIT MAGI threshold | C15: =INDEX('Tax Tables & Assumptions'!$D$29:$G$29,$C$5) -> 250000
B16: NJ rate table used | C16: =INDEX('Tax Tables & Assumptions'!$D$44:$G$44,$C$5) -> B
B17: NJ exemptions (personal + dependents) | C17: =INDEX('Tax Tables & Assumptions'!$D$45:$G$45,$C$5)+MAX(0,N('Client Input'!$C$11))*INDEX('Tax Tables & Assumptions'!$D$46:$G$46,$C$5) -> 2000
B18: NJ standard deduction | C18: =INDEX('Tax Tables & Assumptions'!$D$48:$G$48,$C$5) -> 0 | D18: NJ has none (0).
B19: NJ filing threshold (no tax if NJ gross income ≤) | C19: =INDEX('Tax Tables & Assumptions'!$D$47:$G$47,$C$5) -> 20000
B21: B. INVESTMENT INCOME COMPONENTS (negatives treated as $0)
B22: Component | C22: Amount | D22: Federal: ordinary | E22: Federal: preferential | F22: Federal: exempt | G22: NJ taxable | H22: NJ exempt | J22: NJ treatment
B23: Qualified dividends | C23: =MAX(0,N('Client Input'!$C$19)) -> 20000 | D23: =0 -> 0 | E23: =C23 -> 20000 | F23: =0 -> 0 | G23: =C23 -> 20000 | H23: =C23-G23 -> 0 | J23: Taxable at ordinary NJ rates
B24: Ordinary / non-qualified dividends | C24: =MAX(0,N('Client Input'!$C$20)) -> 5000 | D24: =C24 -> 5000 | E24: =0 -> 0 | F24: =0 -> 0 | G24: =C24 -> 5000 | H24: =C24-G24 -> 0 | J24: Taxable at ordinary NJ rates
B25: Money market income | C25: =MAX(0,N('Client Input'!$C$21)) -> 5000 | D25: =C25 -> 5000 | E25: =0 -> 0 | F25: =0 -> 0 | G25: =C25*(1-MIN(1,MAX(0,N('Client Input'!$C$30)))) -> 5000 | H25: =C25-G25 -> 0 | J25: Taxable except NJ qualified-investment-fund exempt %
B26: Bank / CD interest | C26: =MAX(0,N('Client Input'!$C$22)) -> 10000 | D26: =C26 -> 10000 | E26: =0 -> 0 | F26: =0 -> 0 | G26: =C26 -> 10000 | H26: =C26-G26 -> 0 | J26: Taxable at ordinary NJ rates
B27: Other taxable interest | C27: =MAX(0,N('Client Input'!$C$23)) -> 0 | D27: =C27 -> 0 | E27: =0 -> 0 | F27: =0 -> 0 | G27: =C27 -> 0 | H27: =C27-G27 -> 0 | J27: Taxable at ordinary NJ rates
B28: U.S. Treasury interest | C28: =MAX(0,N('Client Input'!$C$24)) -> 0 | D28: =C28 -> 0 | E28: =0 -> 0 | F28: =0 -> 0 | G28: =0 -> 0 | H28: =C28-G28 -> 0 | J28: Exempt – U.S. obligation
B29: Tax-exempt / municipal interest | C29: =MAX(0,N('Client Input'!$C$25)) -> 0 | D29: =0 -> 0 | E29: =0 -> 0 | F29: =C29 -> 0 | G29: =C29*(1-MIN(1,MAX(0,N('Client Input'!$C$31)))) -> 0 | H29: =C29-G29 -> 0 | J29: Out-of-state portion taxable; NJ-issuer portion exempt
B30: Short-term capital gains | C30: =MAX(0,N('Client Input'!$C$26)) -> 0 | D30: =C30 -> 0 | E30: =0 -> 0 | F30: =0 -> 0 | G30: =C30 -> 0 | H30: =C30-G30 -> 0 | J30: Taxable at ordinary NJ rates
B31: Long-term capital gains | C31: =MAX(0,N('Client Input'!$C$27)) -> 10000 | D31: =0 -> 0 | E31: =C31 -> 10000 | F31: =0 -> 0 | G31: =C31 -> 10000 | H31: =C31-G31 -> 0 | J31: Taxable at ordinary NJ rates
B32: Totals | C32: =SUM(C23:C31) -> 50000 | D32: =SUM(D23:D31) -> 20000 | E32: =SUM(E23:E31) -> 30000 | F32: =SUM(F23:F31) -> 0 | G32: =SUM(G23:G31) -> 50000 | H32: =SUM(H23:H31) -> 0
B33: Ordinary investment income excl. short-term gains | C33: =D32-$C$30 -> 20000
B34: Net investment income for NIIT (all federally taxable investment income) | C34: =$D$32+$E$32 -> 50000
B36: C. FEDERAL ORDINARY BRACKETS FOR THIS FILING STATUS
B37: Bracket | C37: Rate | D37: Taxable income over | E37: Up to | F37: Incremental rate | G37: Income in bracket – BEFORE | H37: Income in bracket – AFTER | I37: Added tax in bracket
B38: Bracket 1 | C38: ='Tax Tables & Assumptions'!$C$8 -> 0.1 | D38: =INDEX('Tax Tables & Assumptions'!$D$8:$G$8,$C$5) -> 0 | E38: =D39 -> 24800 | F38: =C38 -> 0.1 | G38: =MAX(0,MIN($C$49,E38)-D38) -> 24800 | H38: =MAX(0,MIN($G$49,E38)-D38) -> 24800 | I38: =(H38-G38)*C38 -> 0
B39: Bracket 2 | C39: ='Tax Tables & Assumptions'!$C$9 -> 0.12 | D39: =INDEX('Tax Tables & Assumptions'!$D$9:$G$9,$C$5) -> 24800 | E39: =D40 -> 100800 | F39: =C39-C38 -> 0.02 | G39: =MAX(0,MIN($C$49,E39)-D39) -> 76000 | H39: =MAX(0,MIN($G$49,E39)-D39) -> 76000 | I39: =(H39-G39)*C39 -> 0
B40: Bracket 3 | C40: ='Tax Tables & Assumptions'!$C$10 -> 0.22 | D40: =INDEX('Tax Tables & Assumptions'!$D$10:$G$10,$C$5) -> 100800 | E40: =D41 -> 211400 | F40: =C40-C39 -> 0.1 | G40: =MAX(0,MIN($C$49,E40)-D40) -> 49200 | H40: =MAX(0,MIN($G$49,E40)-D40) -> 69200 | I40: =(H40-G40)*C40 -> 4400
B41: Bracket 4 | C41: ='Tax Tables & Assumptions'!$C$11 -> 0.24 | D41: =INDEX('Tax Tables & Assumptions'!$D$11:$G$11,$C$5) -> 211400 | E41: =D42 -> 403550 | F41: =C41-C40 -> 0.02 | G41: =MAX(0,MIN($C$49,E41)-D41) -> 0 | H41: =MAX(0,MIN($G$49,E41)-D41) -> 0 | I41: =(H41-G41)*C41 -> 0
B42: Bracket 5 | C42: ='Tax Tables & Assumptions'!$C$12 -> 0.32 | D42: =INDEX('Tax Tables & Assumptions'!$D$12:$G$12,$C$5) -> 403550 | E42: =D43 -> 512450 | F42: =C42-C41 -> 0.08 | G42: =MAX(0,MIN($C$49,E42)-D42) -> 0 | H42: =MAX(0,MIN($G$49,E42)-D42) -> 0 | I42: =(H42-G42)*C42 -> 0
B43: Bracket 6 | C43: ='Tax Tables & Assumptions'!$C$13 -> 0.35 | D43: =INDEX('Tax Tables & Assumptions'!$D$13:$G$13,$C$5) -> 512450 | E43: =D44 -> 768700 | F43: =C43-C42 -> 0.03 | G43: =MAX(0,MIN($C$49,E43)-D43) -> 0 | H43: =MAX(0,MIN($G$49,E43)-D43) -> 0 | I43: =(H43-G43)*C43 -> 0
B44: Bracket 7 | C44: ='Tax Tables & Assumptions'!$C$14 -> 0.37 | D44: =INDEX('Tax Tables & Assumptions'!$D$14:$G$14,$C$5) -> 768700 | E44: =1000000000000 -> 1000000000000 | F44: =C44-C43 -> 0.02 | G44: =MAX(0,MIN($C$49,E44)-D44) -> 0 | H44: =MAX(0,MIN($G$49,E44)-D44) -> 0 | I44: =(H44-G44)*C44 -> 0
B45: Total ordinary income / added ordinary tax | G45: =SUM(G38:G44) -> 150000 | H45: =SUM(H38:H44) -> 170000 | I45: =SUM(I38:I44) -> 4400 | J45: Shows how ordinary investment income & STCG fill each bracket above existing income.
B47: D. FEDERAL INCOME TAX – BEFORE vs. AFTER INVESTMENT INCOME (income added in stacking order)
B48: Line | C48: 1. BEFORE investment income | D48: 2. + Ordinary interest & dividends | E48: 3. + Short-term gains | F48: 4. + Qualified dividends | G48: 5. + Long-term gains (= AFTER)
B49: Ordinary taxable income (taxed at ordinary rates) | C49: =MAX(0,N('Client Input'!$C$14)) -> 150000 | D49: =C49+$C$33 -> 170000 | E49: =D49+$C$30 -> 170000 | F49: =E49 -> 170000 | G49: =F49 -> 170000
B50: Preferential income (qualified dividends + LTCG) | C50: =0 -> 0 | D50: =0 -> 0 | E50: =0 -> 0 | F50: =$C$23 -> 20000 | G50: =F50+$C$31 -> 30000
B51: Total federal taxable income | C51: =C49+C50 -> 150000 | D51: =D49+D50 -> 170000 | E51: =E49+E50 -> 170000 | F51: =F49+F50 -> 190000 | G51: =G49+G50 -> 200000
B52: Tax on ordinary income (bracket math) | C52: =SUMPRODUCT((C49>$D$38:$D$44)*(C49-$D$38:$D$44)*$F$38:$F$44) -> 22424 | D52: =SUMPRODUCT((D49>$D$38:$D$44)*(D49-$D$38:$D$44)*$F$38:$F$44) -> 26824 | E52: =SUMPRODUCT((E49>$D$38:$D$44)*(E49-$D$38:$D$44)*$F$38:$F$44) -> 26824 | F52: =SUMPRODUCT((F49>$D$38:$D$44)*(F49-$D$38:$D$44)*$F$38:$F$44) -> 26824 | G52: =SUMPRODUCT((G49>$D$38:$D$44)*(G49-$D$38:$D$44)*$F$38:$F$44) -> 26824
B53: Preferential income in 0% tier | C53: =MIN(C50,MAX(0,$C$9-C49)) -> 0 | D53: =MIN(D50,MAX(0,$C$9-D49)) -> 0 | E53: =MIN(E50,MAX(0,$C$9-E49)) -> 0 | F53: =MIN(F50,MAX(0,$C$9-F49)) -> 0 | G53: =MIN(G50,MAX(0,$C$9-G49)) -> 0
B54: Preferential income in 15% tier | C54: =MIN(C50-C53,MAX(0,$C$10-MAX(C49,$C$9))) -> 0 | D54: =MIN(D50-D53,MAX(0,$C$10-MAX(D49,$C$9))) -> 0 | E54: =MIN(E50-E53,MAX(0,$C$10-MAX(E49,$C$9))) -> 0 | F54: =MIN(F50-F53,MAX(0,$C$10-MAX(F49,$C$9))) -> 20000 | G54: =MIN(G50-G53,MAX(0,$C$10-MAX(G49,$C$9))) -> 30000
B55: Preferential income in 20% tier | C55: =C50-C53-C54 -> 0 | D55: =D50-D53-D54 -> 0 | E55: =E50-E53-E54 -> 0 | F55: =F50-F53-F54 -> 0 | G55: =G50-G53-G54 -> 0
B56: Tax on qualified dividends & LTCG (preferential rates) | C56: =C53*$C$11+C54*$C$12+C55*$C$13 -> 0 | D56: =D53*$C$11+D54*$C$12+D55*$C$13 -> 0 | E56: =E53*$C$11+E54*$C$12+E55*$C$13 -> 0 | F56: =F53*$C$11+F54*$C$12+F55*$C$13 -> 3000 | G56: =G53*$C$11+G54*$C$12+G55*$C$13 -> 4500
B57: Total federal income tax (before NIIT) | C57: =C52+C56 -> 22424 | D57: =D52+D56 -> 26824 | E57: =E52+E56 -> 26824 | F57: =F52+F56 -> 29824 | G57: =G52+G56 -> 31324
B58: Added federal income tax from this step | C58: ="—" -> — | D58: =D57-C57 -> 4400 | E58: =E57-D57 -> 0 | F58: =F57-E57 -> 3000 | G58: =G57-F57 -> 1500
B59: Marginal ordinary bracket at top of ordinary income | C59: =INDEX($C$38:$C$44,MATCH(C49,$D$38:$D$44,1)) -> 0.22 | D59: =INDEX($C$38:$C$44,MATCH(D49,$D$38:$D$44,1)) -> 0.22 | E59: =INDEX($C$38:$C$44,MATCH(E49,$D$38:$D$44,1)) -> 0.22 | F59: =INDEX($C$38:$C$44,MATCH(F49,$D$38:$D$44,1)) -> 0.22 | G59: =INDEX($C$38:$C$44,MATCH(G49,$D$38:$D$44,1)) -> 0.22
B60: Marginal preferential rate at top of taxable income | C60: =IF(C51>$C$10,$C$13,IF(C51>$C$9,$C$12,$C$11)) -> 0.15 | D60: =IF(D51>$C$10,$C$13,IF(D51>$C$9,$C$12,$C$11)) -> 0.15 | E60: =IF(E51>$C$10,$C$13,IF(E51>$C$9,$C$12,$C$11)) -> 0.15 | F60: =IF(F51>$C$10,$C$13,IF(F51>$C$9,$C$12,$C$11)) -> 0.15 | G60: =IF(G51>$C$10,$C$13,IF(G51>$C$9,$C$12,$C$11)) -> 0.15
B61: Preferential tiers follow the IRS Qualified Dividends & Capital Gain Tax Worksheet: ordinary income fills the 0%/15% thresholds first; QD/LTCG are stacked on top.
B63: E. FEDERAL TAX ATTRIBUTABLE TO INVESTMENT INCOME
B64: Item | C64: Amount | D64: Rate on income | J64: How calculated
B65: Tax on ordinary investment income (dividends & interest) | C65: =D57-C57 -> 4400 | D65: =IF($C$33>0,C65/$C$33,0) -> 0.22 | J65: Step 2 − Step 1
B66: Tax on short-term capital gains | C66: =E57-D57 -> 0 | D66: =IF($C$30>0,C66/$C$30,0) -> 0 | J66: Step 3 − Step 2
B67: Tax on qualified dividends | C67: =F57-E57 -> 3000 | D67: =IF($C$23>0,C67/$C$23,0) -> 0.15 | J67: Step 4 − Step 3
B68: Tax on long-term capital gains | C68: =G57-F57 -> 1500 | D68: =IF($C$31>0,C68/$C$31,0) -> 0.15 | J68: Step 5 − Step 4
B69: Federal income tax attributable to investment income | C69: =G57-C57 -> 8900 | D69: =IF($C$34>0,C69/$C$34,0) -> 0.178 | J69: Tax AFTER − tax BEFORE (equals the sum of the four lines above).
B71: NIIT – Net Investment Income Tax
B72: Estimated MAGI BEFORE investment income | C72: =C51+$C$8 -> 182200 | J72: Existing taxable income + deduction assumed
B73: Estimated MAGI AFTER investment income | C73: =C72+$C$34 -> 232200 | J73: Adds federally taxable investment income (munis excluded)
B74: NIIT threshold for filing status | C74: =$C$15 -> 250000
B75: MAGI in excess of threshold | C75: =MAX(0,C73-C74) -> 0
B76: NIIT base = lesser of net investment income or excess MAGI | C76: =MIN($C$34,C75) -> 0 | J76: Form 8960 line 17 logic
B77: NIIT (3.8%) | C77: =C76*$C$14 -> 0 | J77: All NIIT is attributable to investment income
B79: TOTAL FEDERAL TAX ON INVESTMENT INCOME (income tax + NIIT) | C79: =$C$69+$C$77 -> 8900 | D79: =IF($C$34>0,C79/$C$34,0) -> 0.178 | J79: Rate shown is on federally taxable investment income.
B82: F. NEW JERSEY GROSS INCOME TAX – BEFORE vs. AFTER INVESTMENT INCOME
B83: NJ bracket | C83: Rate | D83: NJ taxable income over | E83: Up to | F83: Incremental rate | G83: Income in bracket – BEFORE | H83: Income in bracket – AFTER | I83: Added NJ tax in bracket
B84: Bracket 1 | C84: =IF($C$16="A",'Tax Tables & Assumptions'!$D$33,'Tax Tables & Assumptions'!$F$33) -> 0.014 | D84: =IF($C$16="A",IF('Tax Tables & Assumptions'!$C$33="",1000000000000,'Tax Tables & Assumptions'!$C$33),IF('Tax Tables & Assumptions'!$E$33="",1000000000000,'Tax Tables & Assumptions'!$E$33)) -> 0 | E84: =D85 -> 20000 | F84: =C84 -> 0.014 | G84: =MAX(0,MIN($C$95,E84)-D84) -> 20000 | H84: =MAX(0,MIN($D$95,E84)-D84) -> 20000 | I84: =(H84-G84)*C84 -> 0
B85: Bracket 2 | C85: =IF(D85>=1000000000000,C84,IF($C$16="A",'Tax Tables & Assumptions'!$D$34,'Tax Tables & Assumptions'!$F$34)) -> 0.0175 | D85: =IF($C$16="A",IF('Tax Tables & Assumptions'!$C$34="",1000000000000,'Tax Tables & Assumptions'!$C$34),IF('Tax Tables & Assumptions'!$E$34="",1000000000000,'Tax Tables & Assumptions'!$E$34)) -> 20000 | E85: =D86 -> 50000 | F85: =C85-C84 -> 0.0035 | G85: =MAX(0,MIN($C$95,E85)-D85) -> 30000 | H85: =MAX(0,MIN($D$95,E85)-D85) -> 30000 | I85: =(H85-G85)*C85 -> 0
B86: Bracket 3 | C86: =IF(D86>=1000000000000,C85,IF($C$16="A",'Tax Tables & Assumptions'!$D$35,'Tax Tables & Assumptions'!$F$35)) -> 0.0245 | D86: =IF($C$16="A",IF('Tax Tables & Assumptions'!$C$35="",1000000000000,'Tax Tables & Assumptions'!$C$35),IF('Tax Tables & Assumptions'!$E$35="",1000000000000,'Tax Tables & Assumptions'!$E$35)) -> 50000 | E86: =D87 -> 70000 | F86: =C86-C85 -> 0.007 | G86: =MAX(0,MIN($C$95,E86)-D86) -> 20000 | H86: =MAX(0,MIN($D$95,E86)-D86) -> 20000 | I86: =(H86-G86)*C86 -> 0
B87: Bracket 4 | C87: =IF(D87>=1000000000000,C86,IF($C$16="A",'Tax Tables & Assumptions'!$D$36,'Tax Tables & Assumptions'!$F$36)) -> 0.035 | D87: =IF($C$16="A",IF('Tax Tables & Assumptions'!$C$36="",1000000000000,'Tax Tables & Assumptions'!$C$36),IF('Tax Tables & Assumptions'!$E$36="",1000000000000,'Tax Tables & Assumptions'!$E$36)) -> 70000 | E87: =D88 -> 80000 | F87: =C87-C86 -> 0.0105 | G87: =MAX(0,MIN($C$95,E87)-D87) -> 10000 | H87: =MAX(0,MIN($D$95,E87)-D87) -> 10000 | I87: =(H87-G87)*C87 -> 0
B88: Bracket 5 | C88: =IF(D88>=1000000000000,C87,IF($C$16="A",'Tax Tables & Assumptions'!$D$37,'Tax Tables & Assumptions'!$F$37)) -> 0.05525 | D88: =IF($C$16="A",IF('Tax Tables & Assumptions'!$C$37="",1000000000000,'Tax Tables & Assumptions'!$C$37),IF('Tax Tables & Assumptions'!$E$37="",1000000000000,'Tax Tables & Assumptions'!$E$37)) -> 80000 | E88: =D89 -> 150000 | F88: =C88-C87 -> 0.02025 | G88: =MAX(0,MIN($C$95,E88)-D88) -> 70000 | H88: =MAX(0,MIN($D$95,E88)-D88) -> 70000 | I88: =(H88-G88)*C88 -> 0
B89: Bracket 6 | C89: =IF(D89>=1000000000000,C88,IF($C$16="A",'Tax Tables & Assumptions'!$D$38,'Tax Tables & Assumptions'!$F$38)) -> 0.0637 | D89: =IF($C$16="A",IF('Tax Tables & Assumptions'!$C$38="",1000000000000,'Tax Tables & Assumptions'!$C$38),IF('Tax Tables & Assumptions'!$E$38="",1000000000000,'Tax Tables & Assumptions'!$E$38)) -> 150000 | E89: =D90 -> 500000 | F89: =C89-C88 -> 0.00845 | G89: =MAX(0,MIN($C$95,E89)-D89) -> 30200 | H89: =MAX(0,MIN($D$95,E89)-D89) -> 80200 | I89: =(H89-G89)*C89 -> 3185
B90: Bracket 7 | C90: =IF(D90>=1000000000000,C89,IF($C$16="A",'Tax Tables & Assumptions'!$D$39,'Tax Tables & Assumptions'!$F$39)) -> 0.0897 | D90: =IF($C$16="A",IF('Tax Tables & Assumptions'!$C$39="",1000000000000,'Tax Tables & Assumptions'!$C$39),IF('Tax Tables & Assumptions'!$E$39="",1000000000000,'Tax Tables & Assumptions'!$E$39)) -> 500000 | E90: =D91 -> 1000000 | F90: =C90-C89 -> 0.026 | G90: =MAX(0,MIN($C$95,E90)-D90) -> 0 | H90: =MAX(0,MIN($D$95,E90)-D90) -> 0 | I90: =(H90-G90)*C90 -> 0
B91: Bracket 8 | C91: =IF(D91>=1000000000000,C90,IF($C$16="A",'Tax Tables & Assumptions'!$D$40,'Tax Tables & Assumptions'!$F$40)) -> 0.1075 | D91: =IF($C$16="A",IF('Tax Tables & Assumptions'!$C$40="",1000000000000,'Tax Tables & Assumptions'!$C$40),IF('Tax Tables & Assumptions'!$E$40="",1000000000000,'Tax Tables & Assumptions'!$E$40)) -> 1000000 | E91: =1000000000000 -> 1000000000000 | F91: =C91-C90 -> 0.0178 | G91: =MAX(0,MIN($C$95,E91)-D91) -> 0 | H91: =MAX(0,MIN($D$95,E91)-D91) -> 0 | I91: =(H91-G91)*C91 -> 0
B92: Total NJ taxable income / added NJ tax (before threshold test) | G92: =SUM(G84:G91) -> 180200 | H92: =SUM(H84:H91) -> 230200 | I92: =SUM(I84:I91) -> 3185
B94: NJ calculation | C94: BEFORE investment income | D94: AFTER investment income | E94: Difference | J94: How calculated
B95: NJ taxable income | C95: =IF('Client Input'!$C$16="",MAX(0,C51+$C$8-$C$18-$C$17),MAX(0,'Client Input'!$C$16)) -> 180200 | D95: =C95+$G$32 -> 230200 | E95: =D95-C95 -> 50000 | J95: Before: override, or federal taxable income + federal deduction − NJ std. deduction − NJ exemptions. After: + NJ taxable investment income (Section B).
B96: NJ gross income (for filing-threshold test) | C96: =IF('Client Input'!$C$16="",C51+$C$8,C95+$C$17+$C$18) -> 182200 | D96: =C96+$G$32 -> 232200 | E96: =D96-C96 -> 50000 | J96: No NJ tax if gross income ≤ the filing threshold.
B97: NJ tax per rate schedule (bracket math) | C97: =SUMPRODUCT((C95>$D$84:$D$91)*(C95-$D$84:$D$91)*$F$84:$F$91) -> 7436.24 | D97: =SUMPRODUCT((D95>$D$84:$D$91)*(D95-$D$84:$D$91)*$F$84:$F$91) -> 10621.24 | E97: =D97-C97 -> 3185
B98: NJ tax (after filing threshold & residency test) | C98: =IF($C$6=0,0,IF(C96<=$C$19,0,C97)) -> 7436.24 | D98: =IF($C$6=0,0,IF(D96<=$C$19,0,D97)) -> 10621.24 | E98: =D98-C98 -> 3185 | J98: Difference = NJ tax attributable to investment income.
B99: NJ marginal rate | C99: =INDEX($C$84:$C$91,MATCH(C95,$D$84:$D$91,1)) -> 0.0637 | D99: =INDEX($C$84:$C$91,MATCH(D95,$D$84:$D$91,1)) -> 0.0637
B100: NJ tax on investment income as % of NJ taxable investment income | E100: =IF($G$32>0,E98/$G$32,0) -> 0.0637
B102: G. COMBINED RESULTS (feeds the Client Summary)
B103: Federal income tax on investment income | C103: =$C$69 -> 8900
B104: Federal NIIT | C104: =$C$77 -> 0
B105: New Jersey tax on investment income | C105: =$E$98 -> 3185
B106: Total estimated tax on investment income | C106: =$C$103+$C$104+$C$105 -> 12085
B107: After-tax investment income | C107: =$C$32-$C$106 -> 37915
B108: Effective tax rate on total investment income | C108: =IF($C$32>0,$C$106/$C$32,0) -> 0.2417
B109: Effective tax rate on taxable investment income | C109: =IF($C$34>0,$C$106/$C$34,0) -> 0.2417
B110: Check: federal components tie to BEFORE/AFTER difference | C110: =IF(ABS($C$65+$C$66+$C$67+$C$68-$C$69)<0.01,"OK","CHECK") -> OK
B111: Check: component totals tie to Client Input | C111: =IF(ABS($C$32-'Client Input'!$C$40)<0.01,"OK","CHECK – negative inputs clamped to 0") -> OK

Sheet Client Summary
B1: Investment Income Tax Estimate
B2: Federal & New Jersey — High-Level Planning ESTIMATE
B4: Client | C4: =IF('Client Input'!$C$7="","—",'Client Input'!$C$7) -> Sample Client (replace) | E4: ='Client Input'!$C$42 -> ✓ Inputs complete – results are ESTIMATES only
B5: Tax year | C5: =IF('Client Input'!$C$8="","—",'Client Input'!$C$8) -> 2026
B6: Filing status | C6: =IF('Client Input'!$C$9="","—",'Client Input'!$C$9) -> Married Filing Jointly
B7: New Jersey resident | C7: =IF('Client Input'!$C$10="","—",'Client Input'!$C$10) -> Yes
B9: INVESTMENT INCOME SUMMARY | E9: ESTIMATED TAX IMPACT
B10: Qualified dividends | C10: ='Tax Calculation'!$C$23 -> 20000 | E10: Estimated federal income tax | F10: ='Tax Calculation'!$C$103 -> 8900
B11: Ordinary dividends | C11: ='Tax Calculation'!$C$24 -> 5000 | E11: Estimated federal NIIT (3.8%) | F11: ='Tax Calculation'!$C$104 -> 0
B12: Interest income (money market, bank/CD, other) | C12: ='Tax Calculation'!$C$25+'Tax Calculation'!$C$26+'Tax Calculation'!$C$27 -> 15000 | E12: Estimated New Jersey tax | F12: ='Tax Calculation'!$C$105 -> 3185
B13: U.S. Treasury interest | C13: ='Tax Calculation'!$C$28 -> 0 | E13: Estimated total tax | F13: =F10+F11+F12 -> 12085
B14: Tax-exempt (municipal) interest | C14: ='Tax Calculation'!$C$29 -> 0 | E14: Estimated after-tax investment income | F14: =C17-F13 -> 37915
B15: Short-term capital gains | C15: ='Tax Calculation'!$C$30 -> 0 | E15: Effective tax rate on investment income | F15: =IF(C17>0,F13/C17,0) -> 0.2417
B16: Long-term capital gains | C16: ='Tax Calculation'!$C$31 -> 10000
B17: Total investment income | C17: =SUM(C10:C16) -> 50000 | E17: Effective rate = total estimated tax ÷ total investment income (incl. tax-exempt).
B19: FROM GROSS TO AFTER-TAX INVESTMENT INCOME | E19: FEDERAL TAX BY INCOME TYPE
B20: Total investment income | C20: =C17 -> 50000 | E20: Ordinary dividends & taxable interest | F20: ='Tax Calculation'!$C$65 -> 4400
B21: Less: estimated federal tax (income tax + NIIT) | C21: =-(F10+F11) -> -8900 | E21: Short-term capital gains | F21: ='Tax Calculation'!$C$66 -> 0
B22: Less: estimated New Jersey tax | C22: =-F12 -> -3185 | E22: Qualified dividends | F22: ='Tax Calculation'!$C$67 -> 3000
B23: Equals: estimated after-tax investment income | C23: =SUM(C20:C22) -> 37915 | E23: Long-term capital gains | F23: ='Tax Calculation'!$C$68 -> 1500
E24: Net Investment Income Tax | F24: ='Tax Calculation'!$C$77 -> 0
E25: Total federal tax | F25: =SUM(F20:F24) -> 8900
B27: SUMMARY COMPARISON | E27: MARGINAL RATES (AFTER INVESTMENT INCOME)
B28: Category | C28: Amount | E28: Federal ordinary bracket | F28: ='Tax Calculation'!$G$59 -> 0.22
B29: Gross Investment Income | C29: =C17 -> 50000 | E29: Federal QD / LTCG rate | F29: ='Tax Calculation'!$G$60 -> 0.15
B30: Federal Tax (incl. NIIT) | C30: =F10+F11 -> 8900 | E30: NIIT applies? | F30: =IF('Tax Calculation'!$C$77>0,"Yes – 3.8%","No") -> No
B31: NJ Tax | C31: =F12 -> 3185 | E31: New Jersey bracket | F31: =IF('Tax Calculation'!$C$6=0,"n/a",'Tax Calculation'!$D$99) -> 0.0637
B32: Total Estimated Tax | C32: =F13 -> 12085 | E32: NJ-exempt income (Treasury, NJ munis, etc.) | F32: ='Tax Calculation'!$H$32 -> 0
B33: After-Tax Income | C33: =F14 -> 37915
B34: Effective Tax Rate | C34: =F15 -> 0.2417
B36: IMPORTANT DISCLAIMER
B37: This calculator is intended for high-level tax planning and estimation purposes only and is not tax advice or a substitute for professional tax preparation. Actual tax liability may differ based on the taxpayer's complete financial and tax situation, including deductions, credits, other income, tax elections, and changes in federal or New Jersey tax law. Consult the client's tax professional for final tax calculations.
B42: ="Estimate based on "&'Tax Tables & Assumptions'!$C$3&" federal (IRS Rev. Proc. 2025-32, OBBBA) and New Jersey (N.J.S.A. 54A) tax rules. Marginal method: tax with investment income minus tax without it. Assumes the existing income entered is federal taxable income. See the Tax Tables & Assumptions tab." -> Estimate based on 2026 federal (IRS Rev. Proc. 2025-32, OBBBA) and New Jersey (N.J.S.A. 54A) tax rules. Marginal method: tax with investment income minus tax without it. Assumes the existing income entered is federal taxable income. See the Tax Tables & Assumptions tab.

Sheet Tax Tables & Assumptions
B1: Tax Tables & Assumptions
B2: Every blue value on a light-blue background is an editable assumption used by the formulas. Update these cells each year; no formulas need to be rebuilt.
B3: Tax year of these assumptions: | C3: 2026 | D3: ← Every row below is labeled with this tax year (column H).
B4: Legend: | C4: Assumption | D4: Formula
B6: 1. FEDERAL ORDINARY INCOME TAX BRACKETS (taxable income over…)
B7: Bracket | C7: Rate | D7: Single | E7: Married Filing Jointly | F7: Married Filing Separately | G7: Head of Household | H7: Tax Year | I7: Source / Notes
B8: Bracket 1 | C8: 0.1 | D8: 0 | E8: 0 | F8: 0 | G8: 0 | H8: =$C$3 -> 2026 | I8: IRS Rev. Proc. 2025-32 §4.01 (2026 inflation adjustments, incl. One Big Beautiful Bill Act amendments; OBBBA made the 10%–37% rate structure permanent).
B9: Bracket 2 | C9: 0.12 | D9: 12400 | E9: 24800 | F9: 12400 | G9: 17700 | H9: =$C$3 -> 2026 | I9: Each value is the LOWER edge of the bracket (the rate applies to taxable income above it).
B10: Bracket 3 | C10: 0.22 | D10: 50400 | E10: 100800 | F10: 50400 | G10: 67450 | H10: =$C$3 -> 2026
B11: Bracket 4 | C11: 0.24 | D11: 105700 | E11: 211400 | F11: 105700 | G11: 105700 | H11: =$C$3 -> 2026
B12: Bracket 5 | C12: 0.32 | D12: 201775 | E12: 403550 | F12: 201775 | G12: 201750 | H12: =$C$3 -> 2026
B13: Bracket 6 | C13: 0.35 | D13: 256225 | E13: 512450 | F13: 256225 | G13: 256200 | H13: =$C$3 -> 2026
B14: Bracket 7 | C14: 0.37 | D14: 640600 | E14: 768700 | F14: 384350 | G14: 640600 | H14: =$C$3 -> 2026
B16: 2. FEDERAL STANDARD DEDUCTION
B17: Item | D17: Single | E17: Married Filing Jointly | F17: Married Filing Separately | G17: Head of Household | H17: Tax Year | I17: Source / Notes
B18: Standard deduction | D18: 16100 | E18: 32200 | F18: 16100 | G18: 24150 | H18: =$C$3 -> 2026 | I18: Rev. Proc. 2025-32 (as amended by OBBBA). Used only to estimate AGI/MAGI (for NIIT) and NJ gross income. Excludes age 65+/blind add-ons and the OBBBA $6,000 senior deduction.
B20: 3. QUALIFIED DIVIDEND & LONG-TERM CAPITAL GAIN RATES (taxable income over…)
B21: Rate tier | C21: Rate | D21: Single | E21: Married Filing Jointly | F21: Married Filing Separately | G21: Head of Household | H21: Tax Year | I21: Source / Notes
B22: 0% tier | C22: 0 | D22: 0 | E22: 0 | F22: 0 | G22: 0 | H22: =$C$3 -> 2026 | I22: IRC §1(h); Rev. Proc. 2025-32 §4.03. Thresholds apply to TOTAL taxable income (ordinary income fills first; QD/LTCG stack on top).
B23: 15% tier | C23: 0.15 | D23: 49450 | E23: 98900 | F23: 49450 | G23: 66200 | H23: =$C$3 -> 2026 | I23: Qualified dividends use the same rates/thresholds as long-term capital gains (IRC §1(h)(11)).
B24: 20% tier | C24: 0.2 | D24: 545500 | E24: 613700 | F24: 306850 | G24: 579600 | H24: =$C$3 -> 2026 | I24: 25% unrecaptured §1250 gain and 28% collectibles gain are NOT modeled.
B26: 4. NET INVESTMENT INCOME TAX (NIIT)
B27: Item | C27: Rate | D27: Single | E27: Married Filing Jointly | F27: Married Filing Separately | G27: Head of Household | H27: Tax Year | I27: Source / Notes
B28: NIIT rate | C28: 0.038 | H28: =$C$3 -> 2026 | I28: IRC §1411; Form 8960. NIIT = 3.8% × lesser of (net investment income) or (MAGI − threshold).
B29: Modified AGI threshold | D29: 200000 | E29: 250000 | F29: 125000 | G29: 200000 | H29: =$C$3 -> 2026 | I29: Thresholds are set by statute and are NOT indexed for inflation.
B31: 5. NEW JERSEY GROSS INCOME TAX RATE SCHEDULES (NJ taxable income over…)
B32: Bracket | C32: Table A (Single / MFS) – over | D32: Table A rate | E32: Table B (MFJ / HoH) – over | F32: Table B rate | H32: Tax Year | I32: Source / Notes
B33: Bracket 1 | C33: 0 | D33: 0.014 | E33: 0 | F33: 0.014 | H33: =$C$3 -> 2026 | I33: N.J.S.A. 54A:2-1; NJ-1040 Tax Rate Schedules (NJ Division of Taxation). Rates unchanged since 2020 and in effect for 2026 (a 2026 flat-tax bill, A1850, was introduced but not enacted).
B34: Bracket 2 | C34: 20000 | D34: 0.0175 | E34: 20000 | F34: 0.0175 | H34: =$C$3 -> 2026 | I34: Table A has 7 brackets – leave bracket 8 blank. Blank rows are ignored by the formulas.
B35: Bracket 3 | C35: 35000 | D35: 0.035 | E35: 50000 | F35: 0.0245 | H35: =$C$3 -> 2026 | I35: NJ taxes qualified dividends and capital gains at these same ordinary rates (no preferential rate).
B36: Bracket 4 | C36: 40000 | D36: 0.05525 | E36: 70000 | F36: 0.035 | H36: =$C$3 -> 2026
B37: Bracket 5 | C37: 75000 | D37: 0.0637 | E37: 80000 | F37: 0.05525 | H37: =$C$3 -> 2026
B38: Bracket 6 | C38: 500000 | D38: 0.0897 | E38: 150000 | F38: 0.0637 | H38: =$C$3 -> 2026
B39: Bracket 7 | C39: 1000000 | D39: 0.1075 | E39: 500000 | F39: 0.0897 | H39: =$C$3 -> 2026
B40: Bracket 8 | E40: 1000000 | F40: 0.1075 | H40: =$C$3 -> 2026
B42: 6. NEW JERSEY EXEMPTIONS, FILING THRESHOLD & TABLE ASSIGNMENT
B43: Item | D43: Single | E43: Married Filing Jointly | F43: Married Filing Separately | G43: Head of Household | H43: Tax Year | I43: Source / Notes
B44: NJ rate table used (A or B) | D44: A | E44: B | F44: A | G44: B | H44: =$C$3 -> 2026 | I44: NJ-1040 instructions: Table A = Single / MFS; Table B = MFJ / HoH / Qualifying surviving spouse.
B45: Personal exemption(s) – taxpayer (+ spouse if MFJ) | D45: 1000 | E45: 2000 | F45: 1000 | G45: 1000 | H45: =$C$3 -> 2026 | I45: N.J.S.A. 54A:3-1(a): $1,000 per taxpayer; $1,000 for spouse on a joint return.
B46: Dependent exemption (per dependent) | D46: 1500 | E46: 1500 | F46: 1500 | G46: 1500 | H46: =$C$3 -> 2026 | I46: N.J.S.A. 54A:3-1(b): $1,500 per qualified dependent. Age 65+/blind/veteran exemptions not modeled.
B47: Filing threshold – no NJ tax if NJ gross income ≤ | D47: 10000 | E47: 20000 | F47: 10000 | G47: 20000 | H47: =$C$3 -> 2026 | I47: N.J.S.A. 54A:8-3.1: no tax due if gross income ≤ $10,000 (Single/MFS) or ≤ $20,000 (MFJ/HoH).
B48: NJ standard deduction | D48: 0 | E48: 0 | F48: 0 | G48: 0 | H48: =$C$3 -> 2026 | I48: New Jersey has NO standard deduction (property-tax, medical and other NJ deductions not modeled).
B50: 7. NEW JERSEY TREATMENT OF INVESTMENT INCOME (built into the Tax Calculation formulas)
B51: Income type | C51: Federal | D51: New Jersey | H51: Tax Year | I51: NJ rule / source
B52: Qualified dividends | C52: Preferential 0/15/20% | D52: Taxable – ordinary NJ rates | H52: =$C$3 -> 2026 | I52: N.J.S.A. 54A:5-1(f): all dividends are NJ taxable income; no preferential rate.
B53: Ordinary / non-qualified dividends | C53: Ordinary rates | D53: Taxable | H53: =$C$3 -> 2026 | I53: N.J.S.A. 54A:5-1(f).
B54: Money market income | C54: Ordinary rates | D54: Taxable, except exempt % | H54: =$C$3 -> 2026 | I54: Taxable as dividends/interest. Portion from U.S. obligations is exempt ONLY if the fund is a NJ 'qualified investment fund' (N.J.S.A. 54A:6-14.1) – enter that % on Client Input.
B55: Bank / CD & other taxable interest | C55: Ordinary rates | D55: Taxable | H55: =$C$3 -> 2026 | I55: N.J.S.A. 54A:5-1(e).
B56: U.S. Treasury interest | C56: Ordinary rates | D56: EXEMPT | H56: =$C$3 -> 2026 | I56: 31 U.S.C. §3124 and N.J.S.A. 54A:6-14: interest on U.S. government obligations is exempt from NJ tax.
B57: Municipal interest – NJ issuers | C57: Exempt | D57: EXEMPT | H57: =$C$3 -> 2026 | I57: N.J.S.A. 54A:6-14: obligations of NJ and its political subdivisions are exempt.
B58: Municipal interest – other states | C58: Exempt | D58: TAXABLE | H58: =$C$3 -> 2026 | I58: N.J.S.A. 54A:5-1(e) / 54A:6-14: interest on other states' obligations IS NJ taxable (NJ law requires it).
B59: Short-term capital gains | C59: Ordinary rates | D59: Taxable – ordinary NJ rates | H59: =$C$3 -> 2026 | I59: N.J.S.A. 54A:5-1(c): net gains from disposition of property; no ST/LT distinction in NJ.
B60: Long-term capital gains | C60: Preferential 0/15/20% | D60: Taxable – ordinary NJ rates | H60: =$C$3 -> 2026 | I60: N.J.S.A. 54A:5-1(c). NJ losses cannot offset other income categories (not modeled – gains ≥ 0).
B62: 8. METHOD & KEY SIMPLIFYING ASSUMPTIONS
B63: 1. Marginal method: tax is computed WITHOUT investment income and WITH investment income; the difference is the tax attributable to investment income (never 'income × one flat rate').
B64: 2. Federal stacking order: existing ordinary income → ordinary interest & dividends → short-term gains → qualified dividends → long-term gains (IRS Qualified Dividends & Capital Gain Tax Worksheet logic).
B65: 3. 'Ordinary taxable income before investment income' is FEDERAL TAXABLE INCOME (after deductions). If the client's deductions exceed other income, unused deductions that would shelter investment income are not modeled.
B66: 4. Estimated AGI/MAGI = existing taxable income + deduction assumed (standard unless overridden) + taxable investment income. Existing income is assumed to contain no investment income for NIIT purposes.
B67: 5. NJ taxable income (if not overridden) ≈ federal taxable income + federal deduction − NJ exemptions. For precision (e.g., pensions, Social Security, retirement exclusion) enter the NJ override on Client Input.
B68: 6. Capital gains are entered as net gains ≥ 0. Capital losses, the $3,000 loss limit, carryovers, AMT, credits, phase-outs (e.g., OBBBA senior deduction, SALT cap phase-down) and state credits are not modeled.
B69: 7. Foreign tax credit, §199A REIT dividends, and 25%/28% rate gains are not modeled.
B71: 9. SOURCES (tax year 2026)
B72: • IRS Rev. Proc. 2025-32 – 2026 inflation-adjusted brackets, standard deduction, capital-gain breakpoints (incl. One Big Beautiful Bill Act, Pub. L. 119-21). IRS news release, Oct. 2025.
B73: • Internal Revenue Code §1(h) (capital gains/qualified dividends); §1411 & Form 8960 instructions (NIIT); Form 1040 Instructions – Qualified Dividends and Capital Gain Tax Worksheet.
B74: • N.J.S.A. 54A:2-1 (NJ rates), 54A:3-1 (exemptions), 54A:5-1 (income categories), 54A:6-14 & 6-14.1 (exempt obligations; qualified investment funds), 54A:8-3.1 (filing threshold).
... B76: • Figures were current as of September 2026. Verify against the final IRS and NJ Division of Taxation releases before relying on the results, and update this tab each year.

Sheet Test Cases
B1: Test Cases – Formula Verification (2026 rules)
B2: Each case was entered on Client Input and recalculated; results were compared with an independent hand/Python bracket calculation. Values below are a static record, not live formulas.
B4: # | C4: Scenario | D4: Status | E4: Existing TI | F4: QD | G4: Non-qual div | H4: Money mkt | I4: Bank/CD | J4: Other int. | K4: Treasury | L4: Muni | M4: % NJ munis | N4: STCG | O4: LTCG | P4: Fed income tax | Q4: NIIT | R4: NJ tax | S4: Total tax | T4: After-tax | U4: Eff. rate | V4: Independent check – total tax | W4: Match?
B5: 1 | C5: Single, $100k TI + $20k qualified dividends | D5: Single | E5: 100000 | F5: 20000 | G5: 0 | H5: 0 | I5: 0 | J5: 0 | K5: 0 | L5: 0 | M5: 1 | N5: 0 | O5: 0 | P5: 3000 | Q5: 0 | R5: 1274 | S5: 4274 | T5: 15726 | U5: 0.2137 | V5: 4274 | W5: ✓ Match
B6: 2 | C6: MFJ, $150k TI + $50k mixed (QD, non-qual div, money mkt, CD, LTCG) | D6: Married Filing Jointly | E6: 150000 | F6: 20000 | G6: 5000 | H6: 5000 | I6: 10000 | J6: 0 | K6: 0 | L6: 0 | M6: 1 | N6: 0 | O6: 10000 | P6: 8900 | Q6: 0 | R6: 3185 | S6: 12085 | T6: 37915 | U6: 0.2417 | V6: 12085 | W6: ✓ Match
B7: 3 | C7: High income MFJ – NIIT applies ($400k TI; QD, interest, LTCG) | D7: Married Filing Jointly | E7: 400000 | F7: 60000 | G7: 0 | H7: 0 | I7: 40000 | J7: 0 | K7: 0 | L7: 0 | M7: 1 | N7: 0 | O7: 100000 | P7: 36516 | Q7: 7600 | R7: 16125.2 | S7: 60241.2 | T7: 139758.8 | U7: 0.301206 | V7: 60241.2 | W7: ✓ Match
B8: 4 | C8: Single with U.S. Treasury interest ($80k TI; $15k Treasuries, $5k CD) | D8: Single | E8: 80000 | F8: 0 | G8: 0 | H8: 0 | I8: 5000 | J8: 0 | K8: 15000 | L8: 0 | M8: 1 | N8: 0 | O8: 0 | P8: 4400 | Q8: 0 | R8: 318.5 | S8: 4718.5 | T8: 15281.5 | U8: 0.235925 | V8: 4718.5 | W8: ✓ Match
B9: 5 | C9: MFJ with municipal interest ($120k TI; $25k munis – 60% NJ issuers; $5k QD) | D9: Married Filing Jointly | E9: 120000 | F9: 5000 | G9: 0 | H9: 0 | I9: 0 | J9: 0 | K9: 0 | L9: 25000 | M9: 0.6 | N9: 0 | O9: 0 | P9: 750 | Q9: 0 | R9: 955.5 | S9: 1705.5 | T9: 28294.5 | U9: 0.05685 | V9: 1705.5 | W9: ✓ Match
B10: 6 | C10: Head of Household with ST & LT gains ($90k TI; $15k STCG, $30k LTCG) | D10: Head of Household | E10: 90000 | F10: 0 | G10: 0 | H10: 0 | I10: 0 | J10: 0 | K10: 0 | L10: 0 | M10: 1 | N10: 15000 | O10: 30000 | P10: 7800 | Q10: 0 | R10: 2555.12 | S10: 10355.12 | T10: 34644.88 | U10: 0.23011372 | V10: 10355.12 | W10: ✓ Match
B11: 7 | C11: Spec example: Single, $100k TI + $20k QD + $10k interest | D11: Single | E11: 100000 | F11: 20000 | G11: 0 | H11: 0 | I11: 10000 | J11: 0 | K11: 0 | L11: 0 | M11: 1 | N11: 0 | O11: 0 | P11: 5286 | Q11: 0 | R11: 1911 | S11: 7197 | T11: 22803 | U11: 0.2399 | V11: 7197 | W11: ✓ Match
B12: 8 | C12: MFS, low income – 0% LTCG tier & NJ threshold ($5k TI; $20k LTCG, 1 dependent) | D12: Married Filing Separately | E12: 5000 | F12: 0 | G12: 0 | H12: 0 | I12: 0 | J12: 0 | K12: 0 | L12: 0 | M12: 1 | N12: 0 | O12: 20000 | P12: 0 | Q12: 0 | R12: 408.1 | S12: 408.1 | T12: 19591.9 | U12: 0.020405 | V12: 408.1 | W12: ✓ Match
B13: 9 | C13: Single, very high income – 20% tier, 37% bracket, NJ 10.75% ($900k TI; $150k QD, $50k int, $200k LTCG) | D13: Single | E13: 900000 | F13: 150000 | G13: 0 | H13: 0 | I13: 50000 | J13: 0 | K13: 0 | L13: 0 | M13: 1 | N13: 0 | O13: 200000 | P13: 88500 | Q13: 15200 | R13: 41488.78 | S13: 145188.78 | T13: 254811.22 | U13: 0.36297195 | V13: 145188.78 | W13: ✓ Match
B15: Hand check – Case 1 (Single, $100,000 TI + $20,000 QD): ordinary tax on $100,000 = $1,240 + $4,560 + $10,912 = $16,712 (unchanged by QD); QD sit wholly in the 15% tier (TI $120,000 is between $49,450 and $545,500) → $3,000. MAGI ≈ $136,100 < $200,000 → no NIIT. NJ: taxable ≈ $100,000 + $16,100 − $1,000 = $115,100, in the 6.37% bracket → $20,000 × 6.37% = $1,274. Total $4,274 (21.4%).
B16: Case 3 shows NIIT: MAGI ≈ $400,000 + $32,200 + $200,000 = $632,200; excess over $250,000 exceeds NII, so NIIT = 3.8% × $200,000 = $7,600.
B17: Case 4 shows Treasury interest taxed federally (ordinary) but excluded from NJ income; Case 5 shows municipal interest excluded federally, with only the out-of-state share taxed by NJ.
